{
 "custom_fields": [
  {
   "_assign": null,
   "_comments": null,
   "_liked_by": null,
   "_user_tags": null,
   "allow_in_quick_entry": 0,
   "allow_on_submit": 0,
   "bold": 0,
   "collapsible": 0,
   "collapsible_depends_on": null,
   "columns": 0,
   "creation": "2026-06-27 21:08:42.982891",
   "default": null,
   "depends_on": null,
   "description": null,
   "docstatus": 0,
   "dt": "Sales Invoice",
   "fetch_from": null,
   "fetch_if_empty": 0,
   "fieldname": "custom_billing_currency_mode",
   "fieldtype": "Select",
   "hidden": 0,
   "hide_border": 0,
   "hide_days": 0,
   "hide_seconds": 0,
   "idx": 171,
   "ignore_user_permissions": 0,
   "ignore_xss_filter": 0,
   "in_global_search": 0,
   "in_list_view": 0,
   "in_preview": 0,
   "in_standard_filter": 0,
   "insert_after": "custom_billing_to",
   "is_system_generated": 0,
   "is_virtual": 0,
   "label": "Billing Currency Mode",
   "length": 0,
   "link_filters": null,
   "mandatory_depends_on": null,
   "modified": "2026-06-27 21:08:42.982891",
   "modified_by": "Administrator",
   "module": null,
   "name": "Sales Invoice-custom_billing_currency_mode",
   "no_copy": 0,
   "non_negative": 0,
   "options": "USD\nLOCAL\nBOTH",
   "owner": "Administrator",
   "permlevel": 0,
   "placeholder": null,
   "precision": "",
   "print_hide": 0,
   "print_hide_if_no_value": 0,
   "print_width": null,
   "read_only": 0,
   "read_only_depends_on": null,
   "report_hide": 0,
   "reqd": 0,
   "search_index": 0,
   "show_dashboard": 0,
   "sort_options": 0,
   "translatable": 0,
   "unique": 0,
   "width": null
  },
  {
   "_assign": null,
   "_comments": null,
   "_liked_by": null,
   "_user_tags": null,
   "allow_in_quick_entry": 0,
   "allow_on_submit": 0,
   "bold": 0,
   "collapsible": 0,
   "collapsible_depends_on": null,
   "columns": 0,
   "creation": "2026-06-27 14:56:16.798976",
   "default": null,
   "depends_on": null,
   "description": null,
   "docstatus": 0,
   "dt": "Sales Invoice",
   "fetch_from": null,
   "fetch_if_empty": 0,
   "fieldname": "custom_billing_end_date",
   "fieldtype": "Date",
   "hidden": 0,
   "hide_border": 0,
   "hide_days": 0,
   "hide_seconds": 0,
   "idx": 9,
   "ignore_user_permissions": 0,
   "ignore_xss_filter": 0,
   "in_global_search": 0,
   "in_list_view": 0,
   "in_preview": 0,
   "in_standard_filter": 0,
   "insert_after": "custom_billing_start_date",
   "is_system_generated": 0,
   "is_virtual": 0,
   "label": "Billing End Date",
   "length": 0,
   "link_filters": null,
   "mandatory_depends_on": null,
   "modified": "2026-06-27 14:56:16.798976",
   "modified_by": "Administrator",
   "module": null,
   "name": "Sales Invoice-custom_billing_end_date",
   "no_copy": 0,
   "non_negative": 0,
   "options": null,
   "owner": "Administrator",
   "permlevel": 0,
   "placeholder": null,
   "precision": "",
   "print_hide": 0,
   "print_hide_if_no_value": 0,
   "print_width": null,
   "read_only": 0,
   "read_only_depends_on": null,
   "report_hide": 0,
   "reqd": 0,
   "search_index": 0,
   "show_dashboard": 0,
   "sort_options": 0,
   "translatable": 0,
   "unique": 0,
   "width": null
  },
  {
   "_assign": null,
   "_comments": null,
   "_liked_by": null,
   "_user_tags": null,
   "allow_in_quick_entry": 0,
   "allow_on_submit": 0,
   "bold": 0,
   "collapsible": 0,
   "collapsible_depends_on": null,
   "columns": 0,
   "creation": "2026-06-27 21:08:42.109909",
   "default": null,
   "depends_on": null,
   "description": null,
   "docstatus": 0,
   "dt": "Sales Invoice",
   "fetch_from": null,
   "fetch_if_empty": 0,
   "fieldname": "custom_billing_from",
   "fieldtype": "Date",
   "hidden": 0,
   "hide_border": 0,
   "hide_days": 0,
   "hide_seconds": 0,
   "idx": 169,
   "ignore_user_permissions": 0,
   "ignore_xss_filter": 0,
   "in_global_search": 0,
   "in_list_view": 0,
   "in_preview": 0,
   "in_standard_filter": 0,
   "insert_after": "custom_fleet_billing_col1",
   "is_system_generated": 0,
   "is_virtual": 0,
   "label": "Billing From",
   "length": 0,
   "link_filters": null,
   "mandatory_depends_on": null,
   "modified": "2026-06-27 21:08:42.109909",
   "modified_by": "Administrator",
   "module": null,
   "name": "Sales Invoice-custom_billing_from",
   "no_copy": 0,
   "non_negative": 0,
   "options": "",
   "owner": "Administrator",
   "permlevel": 0,
   "placeholder": null,
   "precision": "",
   "print_hide": 0,
   "print_hide_if_no_value": 0,
   "print_width": null,
   "read_only": 0,
   "read_only_depends_on": null,
   "report_hide": 0,
   "reqd": 0,
   "search_index": 0,
   "show_dashboard": 0,
   "sort_options": 0,
   "translatable": 0,
   "unique": 0,
   "width": null
  },
  {
   "_assign": null,
   "_comments": null,
   "_liked_by": null,
   "_user_tags": null,
   "allow_in_quick_entry": 0,
   "allow_on_submit": 0,
   "bold": 0,
   "collapsible": 0,
   "collapsible_depends_on": null,
   "columns": 0,
   "creation": "2026-06-27 21:08:44.678491",
   "default": null,
   "depends_on": null,
   "description": null,
   "docstatus": 0,
   "dt": "Sales Invoice",
   "fetch_from": null,
   "fetch_if_empty": 0,
   "fieldname": "custom_billing_review_status",
   "fieldtype": "Select",
   "hidden": 0,
   "hide_border": 0,
   "hide_days": 0,
   "hide_seconds": 0,
   "idx": 175,
   "ignore_user_permissions": 0,
   "ignore_xss_filter": 0,
   "in_global_search": 0,
   "in_list_view": 0,
   "in_preview": 0,
   "in_standard_filter": 0,
   "insert_after": "custom_fleet_billing_col2",
   "is_system_generated": 0,
   "is_virtual": 0,
   "label": "Billing Review Status",
   "length": 0,
   "link_filters": null,
   "mandatory_depends_on": null,
   "modified": "2026-06-27 21:08:44.678491",
   "modified_by": "Administrator",
   "module": null,
   "name": "Sales Invoice-custom_billing_review_status",
   "no_copy": 0,
   "non_negative": 0,
   "options": "Draft\nIn Review\nApproved\nCancelled",
   "owner": "Administrator",
   "permlevel": 0,
   "placeholder": null,
   "precision": "",
   "print_hide": 0,
   "print_hide_if_no_value": 0,
   "print_width": null,
   "read_only": 0,
   "read_only_depends_on": null,
   "report_hide": 0,
   "reqd": 0,
   "search_index": 0,
   "show_dashboard": 0,
   "sort_options": 0,
   "translatable": 0,
   "unique": 0,
   "width": null
  },
  {
   "_assign": null,
   "_comments": null,
   "_liked_by": null,
   "_user_tags": null,
   "allow_in_quick_entry": 0,
   "allow_on_submit": 0,
   "bold": 0,
   "collapsible": 0,
   "collapsible_depends_on": null,
   "columns": 0,
   "creation": "2026-06-27 14:56:16.317686",
   "default": null,
   "depends_on": null,
   "description": null,
   "docstatus": 0,
   "dt": "Sales Invoice",
   "fetch_from": null,
   "fetch_if_empty": 0,
   "fieldname": "custom_billing_start_date",
   "fieldtype": "Date",
   "hidden": 0,
   "hide_border": 0,
   "hide_days": 0,
   "hide_seconds": 0,
   "idx": 8,
   "ignore_user_permissions": 0,
   "ignore_xss_filter": 0,
   "in_global_search": 0,
   "in_list_view": 0,
   "in_preview": 0,
   "in_standard_filter": 0,
   "insert_after": "company_tax_id",
   "is_system_generated": 0,
   "is_virtual": 0,
   "label": "Billing Start Date",
   "length": 0,
   "link_filters": null,
   "mandatory_depends_on": null,
   "modified": "2026-06-27 14:56:16.317686",
   "modified_by": "Administrator",
   "module": null,
   "name": "Sales Invoice-custom_billing_start_date",
   "no_copy": 0,
   "non_negative": 0,
   "options": null,
   "owner": "Administrator",
   "permlevel": 0,
   "placeholder": null,
   "precision": "",
   "print_hide": 0,
   "print_hide_if_no_value": 0,
   "print_width": null,
   "read_only": 0,
   "read_only_depends_on": null,
   "report_hide": 0,
   "reqd": 0,
   "search_index": 0,
   "show_dashboard": 0,
   "sort_options": 0,
   "translatable": 0,
   "unique": 0,
   "width": null
  },
  {
   "_assign": null,
   "_comments": null,
   "_liked_by": null,
   "_user_tags": null,
   "allow_in_quick_entry": 0,
   "allow_on_submit": 0,
   "bold": 0,
   "collapsible": 0,
   "collapsible_depends_on": null,
   "columns": 0,
   "creation": "2026-06-27 21:08:42.512989",
   "default": null,
   "depends_on": null,
   "description": null,
   "docstatus": 0,
   "dt": "Sales Invoice",
   "fetch_from": null,
   "fetch_if_empty": 0,
   "fieldname": "custom_billing_to",
   "fieldtype": "Date",
   "hidden": 0,
   "hide_border": 0,
   "hide_days": 0,
   "hide_seconds": 0,
   "idx": 170,
   "ignore_user_permissions": 0,
   "ignore_xss_filter": 0,
   "in_global_search": 0,
   "in_list_view": 0,
   "in_preview": 0,
   "in_standard_filter": 0,
   "insert_after": "custom_billing_from",
   "is_system_generated": 0,
   "is_virtual": 0,
   "label": "Billing To",
   "length": 0,
   "link_filters": null,
   "mandatory_depends_on": null,
   "modified": "2026-06-27 21:08:42.512989",
   "modified_by": "Administrator",
   "module": null,
   "name": "Sales Invoice-custom_billing_to",
   "no_copy": 0,
   "non_negative": 0,
   "options": "",
   "owner": "Administrator",
   "permlevel": 0,
   "placeholder": null,
   "precision": "",
   "print_hide": 0,
   "print_hide_if_no_value": 0,
   "print_width": null,
   "read_only": 0,
   "read_only_depends_on": null,
   "report_hide": 0,
   "reqd": 0,
   "search_index": 0,
   "show_dashboard": 0,
   "sort_options": 0,
   "translatable": 0,
   "unique": 0,
   "width": null
  },
  {
   "_assign": null,
   "_comments": null,
   "_liked_by": null,
   "_user_tags": null,
   "allow_in_quick_entry": 0,
   "allow_on_submit": 0,
   "bold": 0,
   "collapsible": 0,
   "collapsible_depends_on": null,
   "columns": 0,
   "creation": "2026-06-27 21:08:45.758724",
   "default": null,
   "depends_on": null,
   "description": null,
   "docstatus": 0,
   "dt": "Sales Invoice",
   "fetch_from": null,
   "fetch_if_empty": 0,
   "fieldname": "custom_conversion_rate",
   "fieldtype": "Float",
   "hidden": 0,
   "hide_border": 0,
   "hide_days": 0,
   "hide_seconds": 0,
   "idx": 177,
   "ignore_user_permissions": 0,
   "ignore_xss_filter": 0,
   "in_global_search": 0,
   "in_list_view": 0,
   "in_preview": 0,
   "in_standard_filter": 0,
   "insert_after": "custom_local_equivalent_amount",
   "is_system_generated": 0,
   "is_virtual": 0,
   "label": "Conversion Rate",
   "length": 0,
   "link_filters": null,
   "mandatory_depends_on": null,
   "modified": "2026-06-27 21:08:45.758724",
   "modified_by": "Administrator",
   "module": null,
   "name": "Sales Invoice-custom_conversion_rate",
   "no_copy": 0,
   "non_negative": 0,
   "options": "",
   "owner": "Administrator",
   "permlevel": 0,
   "placeholder": null,
   "precision": "",
   "print_hide": 0,
   "print_hide_if_no_value": 0,
   "print_width": null,
   "read_only": 0,
   "read_only_depends_on": null,
   "report_hide": 0,
   "reqd": 0,
   "search_index": 0,
   "show_dashboard": 0,
   "sort_options": 0,
   "translatable": 0,
   "unique": 0,
   "width": null
  },
  {
   "_assign": null,
   "_comments": null,
   "_liked_by": null,
   "_user_tags": null,
   "allow_in_quick_entry": 0,
   "allow_on_submit": 0,
   "bold": 0,
   "collapsible": 0,
   "collapsible_depends_on": null,
   "columns": 0,
   "creation": "2026-06-27 21:08:41.771837",
   "default": null,
   "depends_on": null,
   "description": null,
   "docstatus": 0,
   "dt": "Sales Invoice",
   "fetch_from": null,
   "fetch_if_empty": 0,
   "fieldname": "custom_fleet_billing_col1",
   "fieldtype": "Column Break",
   "hidden": 0,
   "hide_border": 0,
   "hide_days": 0,
   "hide_seconds": 0,
   "idx": 168,
   "ignore_user_permissions": 0,
   "ignore_xss_filter": 0,
   "in_global_search": 0,
   "in_list_view": 0,
   "in_preview": 0,
   "in_standard_filter": 0,
   "insert_after": "custom_fleet_billing_config_section",
   "is_system_generated": 0,
   "is_virtual": 0,
   "label": "",
   "length": 0,
   "link_filters": null,
   "mandatory_depends_on": null,
   "modified": "2026-06-27 21:08:41.771837",
   "modified_by": "Administrator",
   "module": null,
   "name": "Sales Invoice-custom_fleet_billing_col1",
   "no_copy": 0,
   "non_negative": 0,
   "options": "",
   "owner": "Administrator",
   "permlevel": 0,
   "placeholder": null,
   "precision": "",
   "print_hide": 0,
   "print_hide_if_no_value": 0,
   "print_width": null,
   "read_only": 0,
   "read_only_depends_on": null,
   "report_hide": 0,
   "reqd": 0,
   "search_index": 0,
   "show_dashboard": 0,
   "sort_options": 0,
   "translatable": 0,
   "unique": 0,
   "width": null
  },
  {
   "_assign": null,
   "_comments": null,
   "_liked_by": null,
   "_user_tags": null,
   "allow_in_quick_entry": 0,
   "allow_on_submit": 0,
   "bold": 0,
   "collapsible": 0,
   "collapsible_depends_on": null,
   "columns": 0,
   "creation": "2026-06-27 21:08:44.209802",
   "default": null,
   "depends_on": null,
   "description": null,
   "docstatus": 0,
   "dt": "Sales Invoice",
   "fetch_from": null,
   "fetch_if_empty": 0,
   "fieldname": "custom_fleet_billing_col2",
   "fieldtype": "Column Break",
   "hidden": 0,
   "hide_border": 0,
   "hide_days": 0,
   "hide_seconds": 0,
   "idx": 174,
   "ignore_user_permissions": 0,
   "ignore_xss_filter": 0,
   "in_global_search": 0,
   "in_list_view": 0,
   "in_preview": 0,
   "in_standard_filter": 0,
   "insert_after": "custom_is_taxed_invoice",
   "is_system_generated": 0,
   "is_virtual": 0,
   "label": "",
   "length": 0,
   "link_filters": null,
   "mandatory_depends_on": null,
   "modified": "2026-06-27 21:08:44.209802",
   "modified_by": "Administrator",
   "module": null,
   "name": "Sales Invoice-custom_fleet_billing_col2",
   "no_copy": 0,
   "non_negative": 0,
   "options": "",
   "owner": "Administrator",
   "permlevel": 0,
   "placeholder": null,
   "precision": "",
   "print_hide": 0,
   "print_hide_if_no_value": 0,
   "print_width": null,
   "read_only": 0,
   "read_only_depends_on": null,
   "report_hide": 0,
   "reqd": 0,
   "search_index": 0,
   "show_dashboard": 0,
   "sort_options": 0,
   "translatable": 0,
   "unique": 0,
   "width": null
  },
  {
   "_assign": null,
   "_comments": null,
   "_liked_by": null,
   "_user_tags": null,
   "allow_in_quick_entry": 0,
   "allow_on_submit": 0,
   "bold": 0,
   "collapsible": 0,
   "collapsible_depends_on": null,
   "columns": 0,
   "creation": "2026-06-27 21:08:41.400770",
   "default": null,
   "depends_on": null,
   "description": null,
   "docstatus": 0,
   "dt": "Sales Invoice",
   "fetch_from": null,
   "fetch_if_empty": 0,
   "fieldname": "custom_fleet_billing_config_section",
   "fieldtype": "Section Break",
   "hidden": 0,
   "hide_border": 0,
   "hide_days": 0,
   "hide_seconds": 0,
   "idx": 167,
   "ignore_user_permissions": 0,
   "ignore_xss_filter": 0,
   "in_global_search": 0,
   "in_list_view": 0,
   "in_preview": 0,
   "in_standard_filter": 0,
   "insert_after": "custom_fleet_billing_tab",
   "is_system_generated": 0,
   "is_virtual": 0,
   "label": "Fleet Billing Configuration",
   "length": 0,
   "link_filters": null,
   "mandatory_depends_on": null,
   "modified": "2026-06-27 21:08:41.400770",
   "modified_by": "Administrator",
   "module": null,
   "name": "Sales Invoice-custom_fleet_billing_config_section",
   "no_copy": 0,
   "non_negative": 0,
   "options": "",
   "owner": "Administrator",
   "permlevel": 0,
   "placeholder": null,
   "precision": "",
   "print_hide": 0,
   "print_hide_if_no_value": 0,
   "print_width": null,
   "read_only": 0,
   "read_only_depends_on": null,
   "report_hide": 0,
   "reqd": 0,
   "search_index": 0,
   "show_dashboard": 0,
   "sort_options": 0,
   "translatable": 0,
   "unique": 0,
   "width": null
  },
  {
   "_assign": null,
   "_comments": null,
   "_liked_by": null,
   "_user_tags": null,
   "allow_in_quick_entry": 0,
   "allow_on_submit": 0,
   "bold": 0,
   "collapsible": 0,
   "collapsible_depends_on": null,
   "columns": 0,
   "creation": "2026-06-27 21:08:40.314426",
   "default": null,
   "depends_on": null,
   "description": null,
   "docstatus": 0,
   "dt": "Sales Invoice",
   "fetch_from": null,
   "fetch_if_empty": 0,
   "fieldname": "custom_fleet_billing_tab",
   "fieldtype": "Tab Break",
   "hidden": 0,
   "hide_border": 0,
   "hide_days": 0,
   "hide_seconds": 0,
   "idx": 166,
   "ignore_user_permissions": 0,
   "ignore_xss_filter": 0,
   "in_global_search": 0,
   "in_list_view": 0,
   "in_preview": 0,
   "in_standard_filter": 0,
   "insert_after": "more_info_tab",
   "is_system_generated": 0,
   "is_virtual": 0,
   "label": "Fleet Billing",
   "length": 0,
   "link_filters": null,
   "mandatory_depends_on": null,
   "modified": "2026-06-27 21:08:40.314426",
   "modified_by": "Administrator",
   "module": null,
   "name": "Sales Invoice-custom_fleet_billing_tab",
   "no_copy": 0,
   "non_negative": 0,
   "options": "",
   "owner": "Administrator",
   "permlevel": 0,
   "placeholder": null,
   "precision": "",
   "print_hide": 0,
   "print_hide_if_no_value": 0,
   "print_width": null,
   "read_only": 0,
   "read_only_depends_on": null,
   "report_hide": 0,
   "reqd": 0,
   "search_index": 0,
   "show_dashboard": 0,
   "sort_options": 0,
   "translatable": 0,
   "unique": 0,
   "width": null
  },
  {
   "_assign": null,
   "_comments": null,
   "_liked_by": null,
   "_user_tags": null,
   "allow_in_quick_entry": 0,
   "allow_on_submit": 0,
   "bold": 0,
   "collapsible": 0,
   "collapsible_depends_on": null,
   "columns": 0,
   "creation": "2026-06-27 21:08:47.272516",
   "default": null,
   "depends_on": null,
   "description": null,
   "docstatus": 0,
   "dt": "Sales Invoice",
   "fetch_from": null,
   "fetch_if_empty": 0,
   "fieldname": "custom_gen_col1",
   "fieldtype": "Column Break",
   "hidden": 0,
   "hide_border": 0,
   "hide_days": 0,
   "hide_seconds": 0,
   "idx": 180,
   "ignore_user_permissions": 0,
   "ignore_xss_filter": 0,
   "in_global_search": 0,
   "in_list_view": 0,
   "in_preview": 0,
   "in_standard_filter": 0,
   "insert_after": "custom_generation_info_section",
   "is_system_generated": 0,
   "is_virtual": 0,
   "label": "",
   "length": 0,
   "link_filters": null,
   "mandatory_depends_on": null,
   "modified": "2026-06-27 21:08:47.272516",
   "modified_by": "Administrator",
   "module": null,
   "name": "Sales Invoice-custom_gen_col1",
   "no_copy": 0,
   "non_negative": 0,
   "options": "",
   "owner": "Administrator",
   "permlevel": 0,
   "placeholder": null,
   "precision": "",
   "print_hide": 0,
   "print_hide_if_no_value": 0,
   "print_width": null,
   "read_only": 0,
   "read_only_depends_on": null,
   "report_hide": 0,
   "reqd": 0,
   "search_index": 0,
   "show_dashboard": 0,
   "sort_options": 0,
   "translatable": 0,
   "unique": 0,
   "width": null
  },
  {
   "_assign": null,
   "_comments": null,
   "_liked_by": null,
   "_user_tags": null,
   "allow_in_quick_entry": 0,
   "allow_on_submit": 0,
   "bold": 0,
   "collapsible": 0,
   "collapsible_depends_on": null,
   "columns": 0,
   "creation": "2026-06-27 21:08:49.017341",
   "default": null,
   "depends_on": null,
   "description": null,
   "docstatus": 0,
   "dt": "Sales Invoice",
   "fetch_from": null,
   "fetch_if_empty": 0,
   "fieldname": "custom_gen_col2",
   "fieldtype": "Column Break",
   "hidden": 0,
   "hide_border": 0,
   "hide_days": 0,
   "hide_seconds": 0,
   "idx": 183,
   "ignore_user_permissions": 0,
   "ignore_xss_filter": 0,
   "in_global_search": 0,
   "in_list_view": 0,
   "in_preview": 0,
   "in_standard_filter": 0,
   "insert_after": "custom_generated_by",
   "is_system_generated": 0,
   "is_virtual": 0,
   "label": "",
   "length": 0,
   "link_filters": null,
   "mandatory_depends_on": null,
   "modified": "2026-06-27 21:08:49.017341",
   "modified_by": "Administrator",
   "module": null,
   "name": "Sales Invoice-custom_gen_col2",
   "no_copy": 0,
   "non_negative": 0,
   "options": "",
   "owner": "Administrator",
   "permlevel": 0,
   "placeholder": null,
   "precision": "",
   "print_hide": 0,
   "print_hide_if_no_value": 0,
   "print_width": null,
   "read_only": 0,
   "read_only_depends_on": null,
   "report_hide": 0,
   "reqd": 0,
   "search_index": 0,
   "show_dashboard": 0,
   "sort_options": 0,
   "translatable": 0,
   "unique": 0,
   "width": null
  },
  {
   "_assign": null,
   "_comments": null,
   "_liked_by": null,
   "_user_tags": null,
   "allow_in_quick_entry": 0,
   "allow_on_submit": 0,
   "bold": 0,
   "collapsible": 0,
   "collapsible_depends_on": null,
   "columns": 0,
   "creation": "2026-06-27 21:08:48.455910",
   "default": null,
   "depends_on": null,
   "description": null,
   "docstatus": 0,
   "dt": "Sales Invoice",
   "fetch_from": null,
   "fetch_if_empty": 0,
   "fieldname": "custom_generated_by",
   "fieldtype": "Link",
   "hidden": 0,
   "hide_border": 0,
   "hide_days": 0,
   "hide_seconds": 0,
   "idx": 182,
   "ignore_user_permissions": 0,
   "ignore_xss_filter": 0,
   "in_global_search": 0,
   "in_list_view": 0,
   "in_preview": 0,
   "in_standard_filter": 0,
   "insert_after": "custom_generated_on",
   "is_system_generated": 0,
   "is_virtual": 0,
   "label": "Generated By",
   "length": 0,
   "link_filters": null,
   "mandatory_depends_on": null,
   "modified": "2026-06-27 21:08:48.455910",
   "modified_by": "Administrator",
   "module": null,
   "name": "Sales Invoice-custom_generated_by",
   "no_copy": 0,
   "non_negative": 0,
   "options": "User",
   "owner": "Administrator",
   "permlevel": 0,
   "placeholder": null,
   "precision": "",
   "print_hide": 0,
   "print_hide_if_no_value": 0,
   "print_width": null,
   "read_only": 0,
   "read_only_depends_on": null,
   "report_hide": 0,
   "reqd": 0,
   "search_index": 0,
   "show_dashboard": 0,
   "sort_options": 0,
   "translatable": 0,
   "unique": 0,
   "width": null
  },
  {
   "_assign": null,
   "_comments": null,
   "_liked_by": null,
   "_user_tags": null,
   "allow_in_quick_entry": 0,
   "allow_on_submit": 0,
   "bold": 0,
   "collapsible": 0,
   "collapsible_depends_on": null,
   "columns": 0,
   "creation": "2026-06-27 21:08:47.806373",
   "default": null,
   "depends_on": null,
   "description": null,
   "docstatus": 0,
   "dt": "Sales Invoice",
   "fetch_from": null,
   "fetch_if_empty": 0,
   "fieldname": "custom_generated_on",
   "fieldtype": "Datetime",
   "hidden": 0,
   "hide_border": 0,
   "hide_days": 0,
   "hide_seconds": 0,
   "idx": 181,
   "ignore_user_permissions": 0,
   "ignore_xss_filter": 0,
   "in_global_search": 0,
   "in_list_view": 0,
   "in_preview": 0,
   "in_standard_filter": 0,
   "insert_after": "custom_gen_col1",
   "is_system_generated": 0,
   "is_virtual": 0,
   "label": "Generated On",
   "length": 0,
   "link_filters": null,
   "mandatory_depends_on": null,
   "modified": "2026-06-27 21:08:47.806373",
   "modified_by": "Administrator",
   "module": null,
   "name": "Sales Invoice-custom_generated_on",
   "no_copy": 0,
   "non_negative": 0,
   "options": "",
   "owner": "Administrator",
   "permlevel": 0,
   "placeholder": null,
   "precision": "",
   "print_hide": 0,
   "print_hide_if_no_value": 0,
   "print_width": null,
   "read_only": 0,
   "read_only_depends_on": null,
   "report_hide": 0,
   "reqd": 0,
   "search_index": 0,
   "show_dashboard": 0,
   "sort_options": 0,
   "translatable": 0,
   "unique": 0,
   "width": null
  },
  {
   "_assign": null,
   "_comments": null,
   "_liked_by": null,
   "_user_tags": null,
   "allow_in_quick_entry": 0,
   "allow_on_submit": 0,
   "bold": 0,
   "collapsible": 0,
   "collapsible_depends_on": null,
   "columns": 0,
   "creation": "2026-06-27 21:08:46.807845",
   "default": null,
   "depends_on": null,
   "description": null,
   "docstatus": 0,
   "dt": "Sales Invoice",
   "fetch_from": null,
   "fetch_if_empty": 0,
   "fieldname": "custom_generation_info_section",
   "fieldtype": "Section Break",
   "hidden": 0,
   "hide_border": 0,
   "hide_days": 0,
   "hide_seconds": 0,
   "idx": 179,
   "ignore_user_permissions": 0,
   "ignore_xss_filter": 0,
   "in_global_search": 0,
   "in_list_view": 0,
   "in_preview": 0,
   "in_standard_filter": 0,
   "insert_after": "custom_requires_physical_copy",
   "is_system_generated": 0,
   "is_virtual": 0,
   "label": "Generation Info",
   "length": 0,
   "link_filters": null,
   "mandatory_depends_on": null,
   "modified": "2026-06-27 21:08:46.807845",
   "modified_by": "Administrator",
   "module": null,
   "name": "Sales Invoice-custom_generation_info_section",
   "no_copy": 0,
   "non_negative": 0,
   "options": "",
   "owner": "Administrator",
   "permlevel": 0,
   "placeholder": null,
   "precision": "",
   "print_hide": 0,
   "print_hide_if_no_value": 0,
   "print_width": null,
   "read_only": 0,
   "read_only_depends_on": null,
   "report_hide": 0,
   "reqd": 0,
   "search_index": 0,
   "show_dashboard": 0,
   "sort_options": 0,
   "translatable": 0,
   "unique": 0,
   "width": null
  },
  {
   "_assign": null,
   "_comments": null,
   "_liked_by": null,
   "_user_tags": null,
   "allow_in_quick_entry": 0,
   "allow_on_submit": 0,
   "bold": 0,
   "collapsible": 0,
   "collapsible_depends_on": null,
   "columns": 0,
   "creation": "2026-06-27 21:08:49.571028",
   "default": null,
   "depends_on": null,
   "description": null,
   "docstatus": 0,
   "dt": "Sales Invoice",
   "fetch_from": null,
   "fetch_if_empty": 0,
   "fieldname": "custom_generation_method",
   "fieldtype": "Select",
   "hidden": 0,
   "hide_border": 0,
   "hide_days": 0,
   "hide_seconds": 0,
   "idx": 184,
   "ignore_user_permissions": 0,
   "ignore_xss_filter": 0,
   "in_global_search": 0,
   "in_list_view": 0,
   "in_preview": 0,
   "in_standard_filter": 0,
   "insert_after": "custom_gen_col2",
   "is_system_generated": 0,
   "is_virtual": 0,
   "label": "Generation Method",
   "length": 0,
   "link_filters": null,
   "mandatory_depends_on": null,
   "modified": "2026-06-27 21:08:49.571028",
   "modified_by": "Administrator",
   "module": null,
   "name": "Sales Invoice-custom_generation_method",
   "no_copy": 0,
   "non_negative": 0,
   "options": "Scheduled\nManual",
   "owner": "Administrator",
   "permlevel": 0,
   "placeholder": null,
   "precision": "",
   "print_hide": 0,
   "print_hide_if_no_value": 0,
   "print_width": null,
   "read_only": 0,
   "read_only_depends_on": null,
   "report_hide": 0,
   "reqd": 0,
   "search_index": 0,
   "show_dashboard": 0,
   "sort_options": 0,
   "translatable": 0,
   "unique": 0,
   "width": null
  },
  {
   "_assign": null,
   "_comments": null,
   "_liked_by": null,
   "_user_tags": null,
   "allow_in_quick_entry": 0,
   "allow_on_submit": 0,
   "bold": 0,
   "collapsible": 0,
   "collapsible_depends_on": null,
   "columns": 0,
   "creation": "2026-06-27 21:08:43.801721",
   "default": null,
   "depends_on": null,
   "description": null,
   "docstatus": 0,
   "dt": "Sales Invoice",
   "fetch_from": null,
   "fetch_if_empty": 0,
   "fieldname": "custom_is_taxed_invoice",
   "fieldtype": "Check",
   "hidden": 0,
   "hide_border": 0,
   "hide_days": 0,
   "hide_seconds": 0,
   "idx": 173,
   "ignore_user_permissions": 0,
   "ignore_xss_filter": 0,
   "in_global_search": 0,
   "in_list_view": 0,
   "in_preview": 0,
   "in_standard_filter": 0,
   "insert_after": "custom_vehicle_group",
   "is_system_generated": 0,
   "is_virtual": 0,
   "label": "Is Taxed Invoice",
   "length": 0,
   "link_filters": null,
   "mandatory_depends_on": null,
   "modified": "2026-06-27 21:08:43.801721",
   "modified_by": "Administrator",
   "module": null,
   "name": "Sales Invoice-custom_is_taxed_invoice",
   "no_copy": 0,
   "non_negative": 0,
   "options": "",
   "owner": "Administrator",
   "permlevel": 0,
   "placeholder": null,
   "precision": "",
   "print_hide": 0,
   "print_hide_if_no_value": 0,
   "print_width": null,
   "read_only": 0,
   "read_only_depends_on": null,
   "report_hide": 0,
   "reqd": 0,
   "search_index": 0,
   "show_dashboard": 0,
   "sort_options": 0,
   "translatable": 0,
   "unique": 0,
   "width": null
  },
  {
   "_assign": null,
   "_comments": null,
   "_liked_by": null,
   "_user_tags": null,
   "allow_in_quick_entry": 0,
   "allow_on_submit": 0,
   "bold": 0,
   "collapsible": 0,
   "collapsible_depends_on": null,
   "columns": 0,
   "creation": "2026-06-27 21:08:45.195346",
   "default": null,
   "depends_on": null,
   "description": null,
   "docstatus": 0,
   "dt": "Sales Invoice",
   "fetch_from": null,
   "fetch_if_empty": 0,
   "fieldname": "custom_local_equivalent_amount",
   "fieldtype": "Currency",
   "hidden": 0,
   "hide_border": 0,
   "hide_days": 0,
   "hide_seconds": 0,
   "idx": 176,
   "ignore_user_permissions": 0,
   "ignore_xss_filter": 0,
   "in_global_search": 0,
   "in_list_view": 0,
   "in_preview": 0,
   "in_standard_filter": 0,
   "insert_after": "custom_billing_review_status",
   "is_system_generated": 0,
   "is_virtual": 0,
   "label": "Local Equivalent Amount",
   "length": 0,
   "link_filters": null,
   "mandatory_depends_on": null,
   "modified": "2026-06-27 21:08:45.195346",
   "modified_by": "Administrator",
   "module": null,
   "name": "Sales Invoice-custom_local_equivalent_amount",
   "no_copy": 0,
   "non_negative": 0,
   "options": "",
   "owner": "Administrator",
   "permlevel": 0,
   "placeholder": null,
   "precision": "",
   "print_hide": 0,
   "print_hide_if_no_value": 0,
   "print_width": null,
   "read_only": 0,
   "read_only_depends_on": null,
   "report_hide": 0,
   "reqd": 0,
   "search_index": 0,
   "show_dashboard": 0,
   "sort_options": 0,
   "translatable": 0,
   "unique": 0,
   "width": null
  },
  {
   "_assign": null,
   "_comments": null,
   "_liked_by": null,
   "_user_tags": null,
   "allow_in_quick_entry": 0,
   "allow_on_submit": 0,
   "bold": 0,
   "collapsible": 0,
   "collapsible_depends_on": null,
   "columns": 0,
   "creation": "2026-06-27 21:08:46.328953",
   "default": null,
   "depends_on": null,
   "description": null,
   "docstatus": 0,
   "dt": "Sales Invoice",
   "fetch_from": null,
   "fetch_if_empty": 0,
   "fieldname": "custom_requires_physical_copy",
   "fieldtype": "Check",
   "hidden": 0,
   "hide_border": 0,
   "hide_days": 0,
   "hide_seconds": 0,
   "idx": 178,
   "ignore_user_permissions": 0,
   "ignore_xss_filter": 0,
   "in_global_search": 0,
   "in_list_view": 0,
   "in_preview": 0,
   "in_standard_filter": 0,
   "insert_after": "custom_conversion_rate",
   "is_system_generated": 0,
   "is_virtual": 0,
   "label": "Requires Physical Copy",
   "length": 0,
   "link_filters": null,
   "mandatory_depends_on": null,
   "modified": "2026-06-27 21:08:46.328953",
   "modified_by": "Administrator",
   "module": null,
   "name": "Sales Invoice-custom_requires_physical_copy",
   "no_copy": 0,
   "non_negative": 0,
   "options": "",
   "owner": "Administrator",
   "permlevel": 0,
   "placeholder": null,
   "precision": "",
   "print_hide": 0,
   "print_hide_if_no_value": 0,
   "print_width": null,
   "read_only": 0,
   "read_only_depends_on": null,
   "report_hide": 0,
   "reqd": 0,
   "search_index": 0,
   "show_dashboard": 0,
   "sort_options": 0,
   "translatable": 0,
   "unique": 0,
   "width": null
  },
  {
   "_assign": null,
   "_comments": null,
   "_liked_by": null,
   "_user_tags": null,
   "allow_in_quick_entry": 0,
   "allow_on_submit": 0,
   "bold": 0,
   "collapsible": 0,
   "collapsible_depends_on": null,
   "columns": 0,
   "creation": "2026-06-27 21:08:43.392972",
   "default": null,
   "depends_on": null,
   "description": null,
   "docstatus": 0,
   "dt": "Sales Invoice",
   "fetch_from": null,
   "fetch_if_empty": 0,
   "fieldname": "custom_vehicle_group",
   "fieldtype": "Select",
   "hidden": 0,
   "hide_border": 0,
   "hide_days": 0,
   "hide_seconds": 0,
   "idx": 172,
   "ignore_user_permissions": 0,
   "ignore_xss_filter": 0,
   "in_global_search": 0,
   "in_list_view": 0,
   "in_preview": 0,
   "in_standard_filter": 0,
   "insert_after": "custom_billing_currency_mode",
   "is_system_generated": 0,
   "is_virtual": 0,
   "label": "Vehicle Group",
   "length": 0,
   "link_filters": null,
   "mandatory_depends_on": null,
   "modified": "2026-06-27 21:08:43.392972",
   "modified_by": "Administrator",
   "module": null,
   "name": "Sales Invoice-custom_vehicle_group",
   "no_copy": 0,
   "non_negative": 0,
   "options": "CB\nLocal\nMixed",
   "owner": "Administrator",
   "permlevel": 0,
   "placeholder": null,
   "precision": "",
   "print_hide": 0,
   "print_hide_if_no_value": 0,
   "print_width": null,
   "read_only": 0,
   "read_only_depends_on": null,
   "report_hide": 0,
   "reqd": 0,
   "search_index": 0,
   "show_dashboard": 0,
   "sort_options": 0,
   "translatable": 0,
   "unique": 0,
   "width": null
  },
  {
   "_assign": null,
   "_comments": null,
   "_liked_by": null,
   "_user_tags": null,
   "allow_in_quick_entry": 0,
   "allow_on_submit": 0,
   "bold": 0,
   "collapsible": 0,
   "collapsible_depends_on": null,
   "columns": 0,
   "creation": "2026-07-14 17:20:00.000000",
   "default": null,
   "depends_on": null,
   "description": null,
   "docstatus": 0,
   "dt": "Sales Invoice",
   "fetch_from": null,
   "fetch_if_empty": 0,
   "fieldname": "custom_branch",
   "fieldtype": "Link",
   "hidden": 0,
   "hide_border": 0,
   "hide_days": 0,
   "hide_seconds": 0,
   "idx": 22,
   "ignore_user_permissions": 0,
   "ignore_xss_filter": 0,
   "in_global_search": 0,
   "in_list_view": 1,
   "in_preview": 0,
   "in_standard_filter": 0,
   "insert_after": "customer_name",
   "is_system_generated": 0,
   "is_virtual": 0,
   "label": "Branch",
   "length": 0,
   "link_filters": null,
   "mandatory_depends_on": null,
   "modified": "2026-07-14 17:20:00.000000",
   "modified_by": "Administrator",
   "module": null,
   "name": "Sales Invoice-custom_branch",
   "no_copy": 0,
   "non_negative": 0,
   "options": "Customer Branch",
   "owner": "Administrator",
   "permlevel": 0,
   "placeholder": null,
   "precision": "",
   "print_hide": 0,
   "print_hide_if_no_value": 0,
   "print_width": null,
   "read_only": 0,
   "read_only_depends_on": null,
   "report_hide": 0,
   "reqd": 0,
   "search_index": 0,
   "show_dashboard": 0,
   "sort_options": 0,
   "translatable": 0,
   "unique": 0,
   "width": null
  },
  {
   "_assign": null,
   "_comments": null,
   "_liked_by": null,
   "_user_tags": null,
   "allow_in_quick_entry": 0,
   "allow_on_submit": 0,
   "bold": 0,
   "collapsible": 0,
   "collapsible_depends_on": null,
   "columns": 0,
   "creation": "2026-07-14 17:20:00.000000",
   "default": null,
   "depends_on": null,
   "description": null,
   "docstatus": 0,
   "dt": "Sales Invoice",
   "fetch_from": "custom_branch.tpin",
   "fetch_if_empty": 0,
   "fieldname": "custom_tpin",
   "fieldtype": "Data",
   "hidden": 0,
   "hide_border": 0,
   "hide_days": 0,
   "hide_seconds": 0,
   "idx": 23,
   "ignore_user_permissions": 0,
   "ignore_xss_filter": 0,
   "in_global_search": 0,
   "in_list_view": 1,
   "in_preview": 0,
   "in_standard_filter": 0,
   "insert_after": "custom_branch",
   "is_system_generated": 0,
   "is_virtual": 0,
   "label": "TPIN",
   "length": 0,
   "link_filters": null,
   "mandatory_depends_on": null,
   "modified": "2026-07-14 17:20:00.000000",
   "modified_by": "Administrator",
   "module": null,
   "name": "Sales Invoice-custom_tpin",
   "no_copy": 0,
   "non_negative": 0,
   "options": null,
   "owner": "Administrator",
   "permlevel": 0,
   "placeholder": null,
   "precision": "",
   "print_hide": 0,
   "print_hide_if_no_value": 0,
   "print_width": null,
   "read_only": 0,
   "read_only_depends_on": null,
   "report_hide": 0,
   "reqd": 0,
   "search_index": 0,
   "show_dashboard": 0,
   "sort_options": 0,
   "translatable": 0,
   "unique": 0,
   "width": null
  }
 ],
 "custom_perms": [],
 "doctype": "Sales Invoice",
 "links": [
  {
   "creation": "2022-01-25 10:29:57.771398",
   "custom": 0,
   "docstatus": 0,
   "group": "Reference",
   "hidden": 0,
   "idx": 1,
   "is_child_table": 0,
   "link_doctype": "POS Invoice",
   "link_fieldname": "consolidated_invoice",
   "modified": "2026-05-27 22:34:20.521097",
   "modified_by": "Administrator",
   "name": "q6dp9rh5go",
   "owner": "Administrator",
   "parent": "Sales Invoice",
   "parent_doctype": null,
   "parentfield": "links",
   "parenttype": "DocType",
   "table_fieldname": null
  }
 ],
 "property_setters": [
  {
   "_assign": null,
   "_comments": null,
   "_liked_by": null,
   "_user_tags": null,
   "creation": "2026-06-06 20:29:03.487006",
   "default_value": null,
   "doc_type": "Sales Invoice",
   "docstatus": 0,
   "doctype_or_field": "DocField",
   "field_name": "additional_discount_account",
   "idx": 0,
   "is_system_generated": 1,
   "modified": "2026-07-02 20:59:44.328216",
   "modified_by": "Administrator",
   "module": null,
   "name": "Sales Invoice-additional_discount_account-hidden",
   "owner": "Administrator",
   "property": "hidden",
   "property_type": "Check",
   "row_name": null,
   "value": "1"
  },
  {
   "_assign": null,
   "_comments": null,
   "_liked_by": null,
   "_user_tags": null,
   "_liked_by": null,
   "_user_tags": null,
   "creation": "2026-06-06 20:29:04.485270",
   "default_value": null,
   "doc_type": "Sales Invoice",
   "docstatus": 0,
   "doctype_or_field": "DocField",
   "field_name": "base_rounded_total",
   "idx": 0,
   "is_system_generated": 1,
   "modified": "2026-07-02 20:59:44.439823",
   "modified_by": "Administrator",
   "module": null,
   "name": "Sales Invoice-base_rounded_total-hidden",
   "owner": "Administrator",
   "property": "hidden",
   "property_type": "Check",
   "row_name": null,
   "value": "0"
  },
  {
   "_assign": null,
   "_comments": null,
   "_liked_by": null,
   "_user_tags": null,
   "creation": "2026-06-06 20:29:04.516537",
   "default_value": null,
   "doc_type": "Sales Invoice",
   "docstatus": 0,
   "doctype_or_field": "DocField",
   "field_name": "base_rounded_total",
   "idx": 0,
   "is_system_generated": 1,
   "modified": "2026-07-02 20:59:44.498768",
   "modified_by": "Administrator",
   "module": null,
   "name": "Sales Invoice-base_rounded_total-print_hide",
   "owner": "Administrator",
   "property": "print_hide",
   "property_type": "Check",
   "row_name": null,
   "value": "1"
  },
  {
   "_assign": null,
   "_comments": null,
   "_liked_by": null,
   "_user_tags": null,
   "creation": "2026-06-06 20:29:04.614048",
   "default_value": null,
   "doc_type": "Sales Invoice",
   "docstatus": 0,
   "doctype_or_field": "DocField",
   "field_name": "disable_rounded_total",
   "idx": 0,
   "is_system_generated": 1,
   "modified": "2026-07-02 20:59:44.563176",
   "modified_by": "Administrator",
   "module": null,
   "name": "Sales Invoice-disable_rounded_total-default",
   "owner": "Administrator",
   "property": "default",
   "property_type": "Text",
   "row_name": null,
   "value": "0"
  },
  {
   "_assign": null,
   "_comments": null,
   "_liked_by": null,
   "_user_tags": null,
   "creation": "2026-06-06 20:29:05.696241",
   "default_value": null,
   "doc_type": "Sales Invoice",
   "docstatus": 0,
   "doctype_or_field": "DocField",
   "field_name": "in_words",
   "idx": 0,
   "is_system_generated": 1,
   "modified": "2026-07-02 20:59:44.627577",
   "modified_by": "Administrator",
   "module": null,
   "name": "Sales Invoice-in_words-hidden",
   "owner": "Administrator",
   "property": "hidden",
   "property_type": "Check",
   "row_name": null,
   "value": "0"
  },
  {
   "_assign": null,
   "_comments": null,
   "_liked_by": null,
   "_user_tags": null,
   "creation": "2026-06-06 20:29:05.729009",
   "default_value": null,
   "doc_type": "Sales Invoice",
   "docstatus": 0,
   "doctype_or_field": "DocField",
   "field_name": "in_words",
   "idx": 0,
   "is_system_generated": 1,
   "modified": "2026-07-02 20:59:44.686213",
   "modified_by": "Administrator",
   "module": null,
   "name": "Sales Invoice-in_words-print_hide",
   "owner": "Administrator",
   "property": "print_hide",
   "property_type": "Check",
   "row_name": null,
   "value": "0"
  },
  {
   "_assign": null,
   "_comments": null,
   "_liked_by": null,
   "_user_tags": null,
   "creation": "2026-06-27 14:56:15.236825",
   "default_value": null,
   "doc_type": "Sales Invoice",
   "docstatus": 0,
   "doctype_or_field": "DocType",
   "field_name": null,
   "idx": 0,
   "is_system_generated": 0,
   "modified": "2026-06-27 14:56:15.236825",
   "modified_by": "Administrator",
   "module": null,
   "name": "Sales Invoice-main-field_order",
   "owner": "Administrator",
   "property": "field_order",
   "property_type": "Data",
   "row_name": null,
   "value": "[\"customer_section\", \"title\", \"naming_series\", \"customer\", \"customer_name\", \"tax_id\", \"company\", \"company_tax_id\", \"billing_start_date\", \"billing_end_date\", \"column_break1\", \"posting_date\", \"posting_time\", \"set_posting_time\", \"due_date\", \"column_break_14\", \"is_pos\", \"pos_profile\", \"is_consolidated\", \"is_return\", \"return_against\", \"update_outstanding_for_self\", \"update_billed_amount_in_sales_order\", \"update_billed_amount_in_delivery_note\", \"is_debit_note\", \"amended_from\", \"accounting_dimensions_section\", \"cost_center\", \"dimension_col_break\", \"project\", \"currency_and_price_list\", \"currency\", \"conversion_rate\", \"column_break2\", \"selling_price_list\", \"price_list_currency\", \"plc_conversion_rate\", \"ignore_pricing_rule\", \"items_section\", \"scan_barcode\", \"update_stock\", \"last_scanned_warehouse\", \"column_break_39\", \"set_warehouse\", \"set_target_warehouse\", \"section_break_42\", \"items\", \"section_break_30\", \"total_qty\", \"total_net_weight\", \"column_break_32\", \"base_total\", \"base_net_total\", \"column_break_52\", \"total\", \"net_total\", \"taxes_section\", \"tax_category\", \"taxes_and_charges\", \"column_break_38\", \"shipping_rule\", \"column_break_55\", \"incoterm\", \"named_place\", \"section_break_40\", \"taxes\", \"section_break_43\", \"base_total_taxes_and_charges\", \"column_break_47\", \"total_taxes_and_charges\", \"totals\", \"base_grand_total\", \"base_rounding_adjustment\", \"base_rounded_total\", \"base_in_words\", \"column_break5\", \"grand_total\", \"rounding_adjustment\", \"use_company_roundoff_cost_center\", \"rounded_total\", \"in_words\", \"total_advance\", \"outstanding_amount\", \"disable_rounded_total\", \"section_break_49\", \"apply_discount_on\", \"base_discount_amount\", \"is_cash_or_non_trade_discount\", \"additional_discount_account\", \"column_break_51\", \"additional_discount_percentage\", \"discount_amount\", \"sec_tax_breakup\", \"other_charges_calculation\", \"pricing_rule_details\", \"pricing_rules\", \"packing_list\", \"packed_items\", \"product_bundle_help\", \"time_sheet_list\", \"timesheets\", \"section_break_104\", \"total_billing_hours\", \"column_break_106\", \"total_billing_amount\", \"payments_tab\", \"payments_section\", \"cash_bank_account\", \"payments\", \"section_break_84\", \"base_paid_amount\", \"column_break_86\", \"paid_amount\", \"section_break_88\", \"base_change_amount\", \"column_break_90\", \"change_amount\", \"account_for_change_amount\", \"advances_section\", \"allocate_advances_automatically\", \"only_include_allocated_payments\", \"get_advances\", \"advances\", \"write_off_section\", \"write_off_amount\", \"base_write_off_amount\", \"write_off_outstanding_amount_automatically\", \"column_break_74\", \"write_off_account\", \"write_off_cost_center\", \"loyalty_points_redemption\", \"redeem_loyalty_points\", \"loyalty_points\", \"loyalty_amount\", \"column_break_77\", \"loyalty_program\", \"loyalty_redemption_account\", \"loyalty_redemption_cost_center\", \"contact_and_address_tab\", \"address_and_contact\", \"customer_address\", \"address_display\", \"col_break4\", \"contact_person\", \"contact_display\", \"contact_mobile\", \"contact_email\", \"territory\", \"shipping_address_section\", \"shipping_address_name\", \"shipping_address\", \"shipping_addr_col_break\", \"dispatch_address_name\", \"dispatch_address\", \"company_address_section\", \"company_address\", \"company_address_display\", \"company_addr_col_break\", \"company_contact_person\", \"terms_tab\", \"payment_schedule_section\", \"ignore_default_payment_terms_template\", \"payment_terms_template\", \"payment_schedule\", \"terms_section_break\", \"tc_name\", \"terms\", \"more_info_tab\", \"customer_po_details\", \"po_no\", \"column_break_23\", \"po_date\", \"more_info\", \"debit_to\", \"party_account_currency\", \"is_opening\", \"column_break8\", \"unrealized_profit_loss_account\", \"against_income_account\", \"sales_team_section_break\", \"sales_partner\", \"amount_eligible_for_commission\", \"column_break10\", \"commission_rate\", \"total_commission\", \"section_break2\", \"sales_team\", \"edit_printing_settings\", \"letter_head\", \"group_same_items\", \"column_break_84\", \"select_print_heading\", \"language\", \"subscription_section\", \"subscription\", \"from_date\", \"auto_repeat\", \"column_break_140\", \"to_date\", \"update_auto_repeat_reference\", \"more_information\", \"status\", \"inter_company_invoice_reference\", \"campaign\", \"represents_company\", \"source\", \"customer_group\", \"col_break23\", \"is_internal_customer\", \"is_discounted\", \"remarks\", \"connections_tab\"]"
  },
  {
   "_assign": null,
   "_comments": null,
   "_liked_by": null,
   "_user_tags": null,
   "creation": "2026-06-06 20:29:04.555915",
   "default_value": null,
   "doc_type": "Sales Invoice",
   "docstatus": 0,
   "doctype_or_field": "DocField",
   "field_name": "rounded_total",
   "idx": 0,
   "is_system_generated": 1,
   "modified": "2026-07-02 20:59:44.741433",
   "modified_by": "Administrator",
   "module": null,
   "name": "Sales Invoice-rounded_total-hidden",
   "owner": "Administrator",
   "property": "hidden",
   "property_type": "Check",
   "row_name": null,
   "value": "0"
  },
  {
   "_assign": null,
   "_comments": null,
   "_liked_by": null,
   "_user_tags": null,
   "creation": "2026-06-06 20:29:04.586013",
   "default_value": null,
   "doc_type": "Sales Invoice",
   "docstatus": 0,
   "doctype_or_field": "DocField",
   "field_name": "rounded_total",
   "idx": 0,
   "is_system_generated": 1,
   "modified": "2026-07-02 20:59:44.797050",
   "modified_by": "Administrator",
   "module": null,
   "name": "Sales Invoice-rounded_total-print_hide",
   "owner": "Administrator",
   "property": "print_hide",
   "property_type": "Check",
   "row_name": null,
   "value": "0"
  },
  {
   "_assign": null,
   "_comments": null,
   "_liked_by": null,
   "_user_tags": null,
   "creation": "2026-06-19 16:50:52.004534",
   "default_value": null,
   "doc_type": "Sales Invoice",
   "docstatus": 0,
   "doctype_or_field": "DocField",
   "field_name": "scan_barcode",
   "idx": 0,
   "is_system_generated": 1,
   "modified": "2026-07-02 20:59:44.858346",
   "modified_by": "Administrator",
   "module": null,
   "name": "Sales Invoice-scan_barcode-hidden",
   "owner": "Administrator",
   "property": "hidden",
   "property_type": "Check",
   "row_name": null,
   "value": "0"
  },
  {
   "_assign": null,
   "_comments": null,
   "_liked_by": null,
   "_user_tags": null,
   "creation": "2026-06-06 20:29:03.218446",
   "default_value": null,
   "doc_type": "Sales Invoice",
   "docstatus": 0,
   "doctype_or_field": "DocField",
   "field_name": "tax_id",
   "idx": 0,
   "is_system_generated": 1,
   "modified": "2026-07-02 20:59:44.926140",
   "modified_by": "Administrator",
   "module": null,
   "name": "Sales Invoice-tax_id-hidden",
   "owner": "Administrator",
   "property": "hidden",
   "property_type": "Check",
   "row_name": null,
   "value": "0"
  },
  {
   "_assign": null,
   "_comments": null,
   "_liked_by": null,
   "_user_tags": null,
   "creation": "2026-06-06 20:29:03.252109",
   "default_value": null,
   "doc_type": "Sales Invoice",
   "docstatus": 0,
   "doctype_or_field": "DocField",
   "field_name": "tax_id",
   "idx": 0,
   "is_system_generated": 1,
   "modified": "2026-07-02 20:59:44.974361",
   "modified_by": "Administrator",
   "module": null,
   "name": "Sales Invoice-tax_id-print_hide",
   "owner": "Administrator",
   "property": "print_hide",
   "property_type": "Check",
   "row_name": null,
   "value": "0"
  }
 ],
 "sync_on_migrate": 1
}