{
 "custom_fields": [
  {
   "_assign": null,
   "_comments": null,
   "_liked_by": null,
   "_user_tags": null,
   "allow_in_quick_entry": 0,
   "allow_on_submit": 0,
   "bold": 0,
   "collapsible": 0,
   "collapsible_depends_on": null,
   "columns": 0,
   "creation": "2026-06-27 21:08:54.436350",
   "default": null,
   "depends_on": null,
   "description": null,
   "docstatus": 0,
   "dt": "Sales Invoice Item",
   "fetch_from": null,
   "fetch_if_empty": 0,
   "fieldname": "custom_billing_attr_col1",
   "fieldtype": "Column Break",
   "hidden": 0,
   "hide_border": 0,
   "hide_days": 0,
   "hide_seconds": 0,
   "idx": 20,
   "ignore_user_permissions": 0,
   "ignore_xss_filter": 0,
   "in_global_search": 0,
   "in_list_view": 0,
   "in_preview": 0,
   "in_standard_filter": 0,
   "insert_after": "custom_billing_attributes_section",
   "is_system_generated": 0,
   "is_virtual": 0,
   "label": "",
   "length": 0,
   "link_filters": null,
   "mandatory_depends_on": null,
   "modified": "2026-06-27 21:08:54.436350",
   "modified_by": "Administrator",
   "module": null,
   "name": "Sales Invoice Item-custom_billing_attr_col1",
   "no_copy": 0,
   "non_negative": 0,
   "options": "",
   "owner": "Administrator",
   "permlevel": 0,
   "placeholder": null,
   "precision": "",
   "print_hide": 0,
   "print_hide_if_no_value": 0,
   "print_width": null,
   "read_only": 0,
   "read_only_depends_on": null,
   "report_hide": 0,
   "reqd": 0,
   "search_index": 0,
   "show_dashboard": 0,
   "sort_options": 0,
   "translatable": 0,
   "unique": 0,
   "width": null
  },
  {
   "_assign": null,
   "_comments": null,
   "_liked_by": null,
   "_user_tags": null,
   "allow_in_quick_entry": 0,
   "allow_on_submit": 0,
   "bold": 0,
   "collapsible": 0,
   "collapsible_depends_on": null,
   "columns": 0,
   "creation": "2026-06-27 21:08:56.096198",
   "default": null,
   "depends_on": null,
   "description": null,
   "docstatus": 0,
   "dt": "Sales Invoice Item",
   "fetch_from": null,
   "fetch_if_empty": 0,
   "fieldname": "custom_billing_attr_col2",
   "fieldtype": "Column Break",
   "hidden": 0,
   "hide_border": 0,
   "hide_days": 0,
   "hide_seconds": 0,
   "idx": 25,
   "ignore_user_permissions": 0,
   "ignore_xss_filter": 0,
   "in_global_search": 0,
   "in_list_view": 0,
   "in_preview": 0,
   "in_standard_filter": 0,
   "insert_after": "custom_included",
   "is_system_generated": 0,
   "is_virtual": 0,
   "label": "",
   "length": 0,
   "link_filters": null,
   "mandatory_depends_on": null,
   "modified": "2026-06-27 21:08:56.096198",
   "modified_by": "Administrator",
   "module": null,
   "name": "Sales Invoice Item-custom_billing_attr_col2",
   "no_copy": 0,
   "non_negative": 0,
   "options": "",
   "owner": "Administrator",
   "permlevel": 0,
   "placeholder": null,
   "precision": "",
   "print_hide": 0,
   "print_hide_if_no_value": 0,
   "print_width": null,
   "read_only": 0,
   "read_only_depends_on": null,
   "report_hide": 0,
   "reqd": 0,
   "search_index": 0,
   "show_dashboard": 0,
   "sort_options": 0,
   "translatable": 0,
   "unique": 0,
   "width": null
  },
  {
   "_assign": null,
   "_comments": null,
   "_liked_by": null,
   "_user_tags": null,
   "allow_in_quick_entry": 0,
   "allow_on_submit": 0,
   "bold": 0,
   "collapsible": 0,
   "collapsible_depends_on": null,
   "columns": 0,
   "creation": "2026-06-27 21:08:54.059266",
   "default": null,
   "depends_on": null,
   "description": null,
   "docstatus": 0,
   "dt": "Sales Invoice Item",
   "fetch_from": null,
   "fetch_if_empty": 0,
   "fieldname": "custom_billing_attributes_section",
   "fieldtype": "Section Break",
   "hidden": 0,
   "hide_border": 0,
   "hide_days": 0,
   "hide_seconds": 0,
   "idx": 19,
   "ignore_user_permissions": 0,
   "ignore_xss_filter": 0,
   "in_global_search": 0,
   "in_list_view": 0,
   "in_preview": 0,
   "in_standard_filter": 0,
   "insert_after": "custom_custom_biling_month",
   "is_system_generated": 0,
   "is_virtual": 0,
   "label": "Billing Attributes",
   "length": 0,
   "link_filters": null,
   "mandatory_depends_on": null,
   "modified": "2026-06-27 21:08:54.059266",
   "modified_by": "Administrator",
   "module": null,
   "name": "Sales Invoice Item-custom_billing_attributes_section",
   "no_copy": 0,
   "non_negative": 0,
   "options": "",
   "owner": "Administrator",
   "permlevel": 0,
   "placeholder": null,
   "precision": "",
   "print_hide": 0,
   "print_hide_if_no_value": 0,
   "print_width": null,
   "read_only": 0,
   "read_only_depends_on": null,
   "report_hide": 0,
   "reqd": 0,
   "search_index": 0,
   "show_dashboard": 0,
   "sort_options": 0,
   "translatable": 0,
   "unique": 0,
   "width": null
  },
  {
   "_assign": null,
   "_comments": null,
   "_liked_by": null,
   "_user_tags": null,
   "allow_in_quick_entry": 0,
   "allow_on_submit": 0,
   "bold": 0,
   "collapsible": 0,
   "collapsible_depends_on": null,
   "columns": 0,
   "creation": "2026-06-27 21:08:56.737740",
   "default": null,
   "depends_on": null,
   "description": null,
   "docstatus": 0,
   "dt": "Sales Invoice Item",
   "fetch_from": null,
   "fetch_if_empty": 0,
   "fieldname": "custom_billing_decision",
   "fieldtype": "Select",
   "hidden": 0,
   "hide_border": 0,
   "hide_days": 0,
   "hide_seconds": 0,
   "idx": 27,
   "ignore_user_permissions": 0,
   "ignore_xss_filter": 0,
   "in_global_search": 0,
   "in_list_view": 0,
   "in_preview": 0,
   "in_standard_filter": 0,
   "insert_after": "custom_rate_code",
   "is_system_generated": 0,
   "is_virtual": 0,
   "label": "Billing Decision",
   "length": 0,
   "link_filters": null,
   "mandatory_depends_on": null,
   "modified": "2026-06-27 21:08:56.737740",
   "modified_by": "Administrator",
   "module": null,
   "name": "Sales Invoice Item-custom_billing_decision",
   "no_copy": 0,
   "non_negative": 0,
   "options": "Chargeable\nUnder Warranty\nWaived\nNon Chargeable",
   "owner": "Administrator",
   "permlevel": 0,
   "placeholder": null,
   "precision": "",
   "print_hide": 0,
   "print_hide_if_no_value": 0,
   "print_width": null,
   "read_only": 0,
   "read_only_depends_on": null,
   "report_hide": 0,
   "reqd": 1,
   "search_index": 0,
   "show_dashboard": 0,
   "sort_options": 0,
   "translatable": 0,
   "unique": 0,
   "width": null
  },
  {
   "_assign": null,
   "_comments": null,
   "_liked_by": null,
   "_user_tags": null,
   "allow_in_quick_entry": 0,
   "allow_on_submit": 0,
   "bold": 0,
   "collapsible": 0,
   "collapsible_depends_on": null,
   "columns": 0,
   "creation": "2026-06-27 21:08:53.722878",
   "default": null,
   "depends_on": null,
   "description": null,
   "docstatus": 0,
   "dt": "Sales Invoice Item",
   "fetch_from": null,
   "fetch_if_empty": 0,
   "fieldname": "custom_billing_month_label",
   "fieldtype": "Data",
   "hidden": 0,
   "hide_border": 0,
   "hide_days": 0,
   "hide_seconds": 0,
   "idx": 17,
   "ignore_user_permissions": 0,
   "ignore_xss_filter": 0,
   "in_global_search": 0,
   "in_list_view": 0,
   "in_preview": 0,
   "in_standard_filter": 0,
   "insert_after": "custom_source_job",
   "is_system_generated": 0,
   "is_virtual": 0,
   "label": "Billing Month Label",
   "length": 0,
   "link_filters": null,
   "mandatory_depends_on": null,
   "modified": "2026-06-27 21:08:53.722878",
   "modified_by": "Administrator",
   "module": null,
   "name": "Sales Invoice Item-custom_billing_month_label",
   "no_copy": 0,
   "non_negative": 0,
   "options": "",
   "owner": "Administrator",
   "permlevel": 0,
   "placeholder": null,
   "precision": "",
   "print_hide": 0,
   "print_hide_if_no_value": 0,
   "print_width": null,
   "read_only": 0,
   "read_only_depends_on": null,
   "report_hide": 0,
   "reqd": 0,
   "search_index": 0,
   "show_dashboard": 0,
   "sort_options": 0,
   "translatable": 0,
   "unique": 0,
   "width": null
  },
  {
   "_assign": null,
   "_comments": null,
   "_liked_by": null,
   "_user_tags": null,
   "allow_in_quick_entry": 0,
   "allow_on_submit": 0,
   "bold": 0,
   "collapsible": 0,
   "collapsible_depends_on": null,
   "columns": 0,
   "creation": "2026-07-02 21:13:12.998680",
   "default": null,
   "depends_on": null,
   "description": null,
   "docstatus": 0,
   "dt": "Sales Invoice Item",
   "fetch_from": null,
   "fetch_if_empty": 0,
   "fieldname": "custom_custom_biling_month",
   "fieldtype": "Int",
   "hidden": 0,
   "hide_border": 0,
   "hide_days": 0,
   "hide_seconds": 0,
   "idx": 18,
   "ignore_user_permissions": 0,
   "ignore_xss_filter": 0,
   "in_global_search": 0,
   "in_list_view": 0,
   "in_preview": 0,
   "in_standard_filter": 0,
   "insert_after": "custom_billing_month_label",
   "is_system_generated": 0,
   "is_virtual": 0,
   "label": "Billing Month",
   "length": 0,
   "link_filters": null,
   "mandatory_depends_on": null,
   "modified": "2026-07-02 21:13:12.998680",
   "modified_by": "Administrator",
   "module": null,
   "name": "Sales Invoice Item-custom_custom_biling_month",
   "no_copy": 0,
   "non_negative": 0,
   "options": null,
   "owner": "Administrator",
   "permlevel": 0,
   "placeholder": null,
   "precision": "",
   "print_hide": 0,
   "print_hide_if_no_value": 0,
   "print_width": null,
   "read_only": 0,
   "read_only_depends_on": null,
   "report_hide": 0,
   "reqd": 0,
   "search_index": 0,
   "show_dashboard": 0,
   "sort_options": 0,
   "translatable": 0,
   "unique": 0,
   "width": null
  },
  {
   "_assign": null,
   "_comments": null,
   "_liked_by": null,
   "_user_tags": null,
   "allow_in_quick_entry": 0,
   "allow_on_submit": 0,
   "bold": 0,
   "collapsible": 0,
   "collapsible_depends_on": null,
   "columns": 0,
   "creation": "2026-06-27 21:08:51.171464",
   "default": null,
   "depends_on": null,
   "description": null,
   "docstatus": 0,
   "dt": "Sales Invoice Item",
   "fetch_from": null,
   "fetch_if_empty": 0,
   "fieldname": "custom_device_number",
   "fieldtype": "Data",
   "hidden": 0,
   "hide_border": 0,
   "hide_days": 0,
   "hide_seconds": 0,
   "idx": 12,
   "ignore_user_permissions": 0,
   "ignore_xss_filter": 0,
   "in_global_search": 0,
   "in_list_view": 0,
   "in_preview": 0,
   "in_standard_filter": 0,
   "insert_after": "custom_vehicle",
   "is_system_generated": 0,
   "is_virtual": 0,
   "label": "Device Number",
   "length": 0,
   "link_filters": null,
   "mandatory_depends_on": null,
   "modified": "2026-06-27 21:08:51.171464",
   "modified_by": "Administrator",
   "module": null,
   "name": "Sales Invoice Item-custom_device_number",
   "no_copy": 0,
   "non_negative": 0,
   "options": "",
   "owner": "Administrator",
   "permlevel": 0,
   "placeholder": null,
   "precision": "",
   "print_hide": 0,
   "print_hide_if_no_value": 0,
   "print_width": null,
   "read_only": 0,
   "read_only_depends_on": null,
   "report_hide": 0,
   "reqd": 0,
   "search_index": 0,
   "show_dashboard": 0,
   "sort_options": 0,
   "translatable": 0,
   "unique": 0,
   "width": null
  },
  {
   "_assign": null,
   "_comments": null,
   "_liked_by": null,
   "_user_tags": null,
   "allow_in_quick_entry": 0,
   "allow_on_submit": 0,
   "bold": 0,
   "collapsible": 0,
   "collapsible_depends_on": null,
   "columns": 0,
   "creation": "2026-06-27 21:08:58.153893",
   "default": null,
   "depends_on": null,
   "description": null,
   "docstatus": 0,
   "dt": "Sales Invoice Item",
   "fetch_from": null,
   "fetch_if_empty": 0,
   "fieldname": "custom_final_rate",
   "fieldtype": "Currency",
   "hidden": 0,
   "hide_border": 0,
   "hide_days": 0,
   "hide_seconds": 0,
   "idx": 31,
   "ignore_user_permissions": 0,
   "ignore_xss_filter": 0,
   "in_global_search": 0,
   "in_list_view": 0,
   "in_preview": 0,
   "in_standard_filter": 0,
   "insert_after": "custom_original_rate",
   "is_system_generated": 0,
   "is_virtual": 0,
   "label": "Final Rate",
   "length": 0,
   "link_filters": null,
   "mandatory_depends_on": null,
   "modified": "2026-06-27 21:08:58.153893",
   "modified_by": "Administrator",
   "module": null,
   "name": "Sales Invoice Item-custom_final_rate",
   "no_copy": 0,
   "non_negative": 0,
   "options": "",
   "owner": "Administrator",
   "permlevel": 0,
   "placeholder": null,
   "precision": "",
   "print_hide": 0,
   "print_hide_if_no_value": 0,
   "print_width": null,
   "read_only": 0,
   "read_only_depends_on": null,
   "report_hide": 0,
   "reqd": 0,
   "search_index": 0,
   "show_dashboard": 0,
   "sort_options": 0,
   "translatable": 0,
   "unique": 0,
   "width": null
  },
  {
   "_assign": null,
   "_comments": null,
   "_liked_by": null,
   "_user_tags": null,
   "allow_in_quick_entry": 0,
   "allow_on_submit": 0,
   "bold": 0,
   "collapsible": 0,
   "collapsible_depends_on": null,
   "columns": 0,
   "creation": "2026-06-27 21:08:50.352504",
   "default": null,
   "depends_on": null,
   "description": null,
   "docstatus": 0,
   "dt": "Sales Invoice Item",
   "fetch_from": null,
   "fetch_if_empty": 0,
   "fieldname": "custom_fleet_details_col1",
   "fieldtype": "Column Break",
   "hidden": 0,
   "hide_border": 0,
   "hide_days": 0,
   "hide_seconds": 0,
   "idx": 10,
   "ignore_user_permissions": 0,
   "ignore_xss_filter": 0,
   "in_global_search": 0,
   "in_list_view": 0,
   "in_preview": 0,
   "in_standard_filter": 0,
   "insert_after": "custom_fleet_details_section",
   "is_system_generated": 0,
   "is_virtual": 0,
   "label": "",
   "length": 0,
   "link_filters": null,
   "mandatory_depends_on": null,
   "modified": "2026-06-27 21:08:50.352504",
   "modified_by": "Administrator",
   "module": null,
   "name": "Sales Invoice Item-custom_fleet_details_col1",
   "no_copy": 0,
   "non_negative": 0,
   "options": "",
   "owner": "Administrator",
   "permlevel": 0,
   "placeholder": null,
   "precision": "",
   "print_hide": 0,
   "print_hide_if_no_value": 0,
   "print_width": null,
   "read_only": 0,
   "read_only_depends_on": null,
   "report_hide": 0,
   "reqd": 0,
   "search_index": 0,
   "show_dashboard": 0,
   "sort_options": 0,
   "translatable": 0,
   "unique": 0,
   "width": null
  },
  {
   "_assign": null,
   "_comments": null,
   "_liked_by": null,
   "_user_tags": null,
   "allow_in_quick_entry": 0,
   "allow_on_submit": 0,
   "bold": 0,
   "collapsible": 0,
   "collapsible_depends_on": null,
   "columns": 0,
   "creation": "2026-06-27 21:08:52.676952",
   "default": null,
   "depends_on": null,
   "description": null,
   "docstatus": 0,
   "dt": "Sales Invoice Item",
   "fetch_from": null,
   "fetch_if_empty": 0,
   "fieldname": "custom_fleet_details_col2",
   "fieldtype": "Column Break",
   "hidden": 0,
   "hide_border": 0,
   "hide_days": 0,
   "hide_seconds": 0,
   "idx": 15,
   "ignore_user_permissions": 0,
   "ignore_xss_filter": 0,
   "in_global_search": 0,
   "in_list_view": 0,
   "in_preview": 0,
   "in_standard_filter": 0,
   "insert_after": "custom_registration_number",
   "is_system_generated": 0,
   "is_virtual": 0,
   "label": "",
   "length": 0,
   "link_filters": null,
   "mandatory_depends_on": null,
   "modified": "2026-06-27 21:08:52.676952",
   "modified_by": "Administrator",
   "module": null,
   "name": "Sales Invoice Item-custom_fleet_details_col2",
   "no_copy": 0,
   "non_negative": 0,
   "options": "",
   "owner": "Administrator",
   "permlevel": 0,
   "placeholder": null,
   "precision": "",
   "print_hide": 0,
   "print_hide_if_no_value": 0,
   "print_width": null,
   "read_only": 0,
   "read_only_depends_on": null,
   "report_hide": 0,
   "reqd": 0,
   "search_index": 0,
   "show_dashboard": 0,
   "sort_options": 0,
   "translatable": 0,
   "unique": 0,
   "width": null
  },
  {
   "_assign": null,
   "_comments": null,
   "_liked_by": null,
   "_user_tags": null,
   "allow_in_quick_entry": 0,
   "allow_on_submit": 0,
   "bold": 0,
   "collapsible": 0,
   "collapsible_depends_on": null,
   "columns": 0,
   "creation": "2026-06-27 21:08:49.991263",
   "default": null,
   "depends_on": null,
   "description": null,
   "docstatus": 0,
   "dt": "Sales Invoice Item",
   "fetch_from": null,
   "fetch_if_empty": 0,
   "fieldname": "custom_fleet_details_section",
   "fieldtype": "Section Break",
   "hidden": 0,
   "hide_border": 0,
   "hide_days": 0,
   "hide_seconds": 0,
   "idx": 9,
   "ignore_user_permissions": 0,
   "ignore_xss_filter": 0,
   "in_global_search": 0,
   "in_list_view": 0,
   "in_preview": 0,
   "in_standard_filter": 0,
   "insert_after": "description",
   "is_system_generated": 0,
   "is_virtual": 0,
   "label": "Fleet Details",
   "length": 0,
   "link_filters": null,
   "mandatory_depends_on": null,
   "modified": "2026-06-27 21:08:49.991263",
   "modified_by": "Administrator",
   "module": null,
   "name": "Sales Invoice Item-custom_fleet_details_section",
   "no_copy": 0,
   "non_negative": 0,
   "options": "",
   "owner": "Administrator",
   "permlevel": 0,
   "placeholder": null,
   "precision": "",
   "print_hide": 0,
   "print_hide_if_no_value": 0,
   "print_width": null,
   "read_only": 0,
   "read_only_depends_on": null,
   "report_hide": 0,
   "reqd": 0,
   "search_index": 0,
   "show_dashboard": 0,
   "sort_options": 0,
   "translatable": 0,
   "unique": 0,
   "width": null
  },
  {
   "_assign": null,
   "_comments": null,
   "_liked_by": null,
   "_user_tags": null,
   "allow_in_quick_entry": 0,
   "allow_on_submit": 0,
   "bold": 0,
   "collapsible": 0,
   "collapsible_depends_on": null,
   "columns": 0,
   "creation": "2026-06-27 21:08:51.485621",
   "default": null,
   "depends_on": null,
   "description": null,
   "docstatus": 0,
   "dt": "Sales Invoice Item",
   "fetch_from": null,
   "fetch_if_empty": 0,
   "fieldname": "custom_fleet_number",
   "fieldtype": "Data",
   "hidden": 0,
   "hide_border": 0,
   "hide_days": 0,
   "hide_seconds": 0,
   "idx": 13,
   "ignore_user_permissions": 0,
   "ignore_xss_filter": 0,
   "in_global_search": 0,
   "in_list_view": 0,
   "in_preview": 0,
   "in_standard_filter": 0,
   "insert_after": "custom_device_number",
   "is_system_generated": 0,
   "is_virtual": 0,
   "label": "Fleet Number",
   "length": 0,
   "link_filters": null,
   "mandatory_depends_on": null,
   "modified": "2026-06-27 21:08:51.485621",
   "modified_by": "Administrator",
   "module": null,
   "name": "Sales Invoice Item-custom_fleet_number",
   "no_copy": 0,
   "non_negative": 0,
   "options": "",
   "owner": "Administrator",
   "permlevel": 0,
   "placeholder": null,
   "precision": "",
   "print_hide": 0,
   "print_hide_if_no_value": 0,
   "print_width": null,
   "read_only": 0,
   "read_only_depends_on": null,
   "report_hide": 0,
   "reqd": 0,
   "search_index": 0,
   "show_dashboard": 0,
   "sort_options": 0,
   "translatable": 0,
   "unique": 0,
   "width": null
  },
  {
   "_assign": null,
   "_comments": null,
   "_liked_by": null,
   "_user_tags": null,
   "allow_in_quick_entry": 0,
   "allow_on_submit": 0,
   "bold": 0,
   "collapsible": 0,
   "collapsible_depends_on": null,
   "columns": 0,
   "creation": "2026-06-27 21:08:55.739624",
   "default": null,
   "depends_on": null,
   "description": null,
   "docstatus": 0,
   "dt": "Sales Invoice Item",
   "fetch_from": null,
   "fetch_if_empty": 0,
   "fieldname": "custom_included",
   "fieldtype": "Check",
   "hidden": 0,
   "hide_border": 0,
   "hide_days": 0,
   "hide_seconds": 0,
   "idx": 24,
   "ignore_user_permissions": 0,
   "ignore_xss_filter": 0,
   "in_global_search": 0,
   "in_list_view": 0,
   "in_preview": 0,
   "in_standard_filter": 0,
   "insert_after": "custom_is_component",
   "is_system_generated": 0,
   "is_virtual": 0,
   "label": "Included",
   "length": 0,
   "link_filters": null,
   "mandatory_depends_on": null,
   "modified": "2026-06-27 21:08:55.739624",
   "modified_by": "Administrator",
   "module": null,
   "name": "Sales Invoice Item-custom_included",
   "no_copy": 0,
   "non_negative": 0,
   "options": "",
   "owner": "Administrator",
   "permlevel": 0,
   "placeholder": null,
   "precision": "",
   "print_hide": 0,
   "print_hide_if_no_value": 0,
   "print_width": null,
   "read_only": 0,
   "read_only_depends_on": null,
   "report_hide": 0,
   "reqd": 0,
   "search_index": 0,
   "show_dashboard": 0,
   "sort_options": 0,
   "translatable": 0,
   "unique": 0,
   "width": null
  },
  {
   "_assign": null,
   "_comments": null,
   "_liked_by": null,
   "_user_tags": null,
   "allow_in_quick_entry": 0,
   "allow_on_submit": 0,
   "bold": 0,
   "collapsible": 0,
   "collapsible_depends_on": null,
   "columns": 0,
   "creation": "2026-06-27 21:08:55.430904",
   "default": null,
   "depends_on": null,
   "description": null,
   "docstatus": 0,
   "dt": "Sales Invoice Item",
   "fetch_from": null,
   "fetch_if_empty": 0,
   "fieldname": "custom_is_component",
   "fieldtype": "Check",
   "hidden": 0,
   "hide_border": 0,
   "hide_days": 0,
   "hide_seconds": 0,
   "idx": 23,
   "ignore_user_permissions": 0,
   "ignore_xss_filter": 0,
   "in_global_search": 0,
   "in_list_view": 0,
   "in_preview": 0,
   "in_standard_filter": 0,
   "insert_after": "custom_is_installation",
   "is_system_generated": 0,
   "is_virtual": 0,
   "label": "Is Component",
   "length": 0,
   "link_filters": null,
   "mandatory_depends_on": null,
   "modified": "2026-06-27 21:08:55.430904",
   "modified_by": "Administrator",
   "module": null,
   "name": "Sales Invoice Item-custom_is_component",
   "no_copy": 0,
   "non_negative": 0,
   "options": "",
   "owner": "Administrator",
   "permlevel": 0,
   "placeholder": null,
   "precision": "",
   "print_hide": 0,
   "print_hide_if_no_value": 0,
   "print_width": null,
   "read_only": 0,
   "read_only_depends_on": null,
   "report_hide": 0,
   "reqd": 0,
   "search_index": 0,
   "show_dashboard": 0,
   "sort_options": 0,
   "translatable": 0,
   "unique": 0,
   "width": null
  },
  {
   "_assign": null,
   "_comments": null,
   "_liked_by": null,
   "_user_tags": null,
   "allow_in_quick_entry": 0,
   "allow_on_submit": 0,
   "bold": 0,
   "collapsible": 0,
   "collapsible_depends_on": null,
   "columns": 0,
   "creation": "2026-06-27 21:08:55.059137",
   "default": null,
   "depends_on": null,
   "description": null,
   "docstatus": 0,
   "dt": "Sales Invoice Item",
   "fetch_from": null,
   "fetch_if_empty": 0,
   "fieldname": "custom_is_installation",
   "fieldtype": "Check",
   "hidden": 0,
   "hide_border": 0,
   "hide_days": 0,
   "hide_seconds": 0,
   "idx": 22,
   "ignore_user_permissions": 0,
   "ignore_xss_filter": 0,
   "in_global_search": 0,
   "in_list_view": 0,
   "in_preview": 0,
   "in_standard_filter": 0,
   "insert_after": "custom_is_subscription",
   "is_system_generated": 0,
   "is_virtual": 0,
   "label": "Is Installation",
   "length": 0,
   "link_filters": null,
   "mandatory_depends_on": null,
   "modified": "2026-06-27 21:08:55.059137",
   "modified_by": "Administrator",
   "module": null,
   "name": "Sales Invoice Item-custom_is_installation",
   "no_copy": 0,
   "non_negative": 0,
   "options": "",
   "owner": "Administrator",
   "permlevel": 0,
   "placeholder": null,
   "precision": "",
   "print_hide": 0,
   "print_hide_if_no_value": 0,
   "print_width": null,
   "read_only": 0,
   "read_only_depends_on": null,
   "report_hide": 0,
   "reqd": 0,
   "search_index": 0,
   "show_dashboard": 0,
   "sort_options": 0,
   "translatable": 0,
   "unique": 0,
   "width": null
  },
  {
   "_assign": null,
   "_comments": null,
   "_liked_by": null,
   "_user_tags": null,
   "allow_in_quick_entry": 0,
   "allow_on_submit": 0,
   "bold": 0,
   "collapsible": 0,
   "collapsible_depends_on": null,
   "columns": 0,
   "creation": "2026-06-27 21:08:54.749090",
   "default": null,
   "depends_on": null,
   "description": null,
   "docstatus": 0,
   "dt": "Sales Invoice Item",
   "fetch_from": null,
   "fetch_if_empty": 0,
   "fieldname": "custom_is_subscription",
   "fieldtype": "Check",
   "hidden": 0,
   "hide_border": 0,
   "hide_days": 0,
   "hide_seconds": 0,
   "idx": 21,
   "ignore_user_permissions": 0,
   "ignore_xss_filter": 0,
   "in_global_search": 0,
   "in_list_view": 0,
   "in_preview": 0,
   "in_standard_filter": 0,
   "insert_after": "custom_billing_attr_col1",
   "is_system_generated": 0,
   "is_virtual": 0,
   "label": "Is Subscription",
   "length": 0,
   "link_filters": null,
   "mandatory_depends_on": null,
   "modified": "2026-06-27 21:08:54.749090",
   "modified_by": "Administrator",
   "module": null,
   "name": "Sales Invoice Item-custom_is_subscription",
   "no_copy": 0,
   "non_negative": 0,
   "options": "",
   "owner": "Administrator",
   "permlevel": 0,
   "placeholder": null,
   "precision": "",
   "print_hide": 0,
   "print_hide_if_no_value": 0,
   "print_width": null,
   "read_only": 0,
   "read_only_depends_on": null,
   "report_hide": 0,
   "reqd": 0,
   "search_index": 0,
   "show_dashboard": 0,
   "sort_options": 0,
   "translatable": 0,
   "unique": 0,
   "width": null
  },
  {
   "_assign": null,
   "_comments": null,
   "_liked_by": null,
   "_user_tags": null,
   "allow_in_quick_entry": 0,
   "allow_on_submit": 0,
   "bold": 0,
   "collapsible": 0,
   "collapsible_depends_on": null,
   "columns": 0,
   "creation": "2026-06-27 21:08:57.780177",
   "default": null,
   "depends_on": null,
   "description": null,
   "docstatus": 0,
   "dt": "Sales Invoice Item",
   "fetch_from": null,
   "fetch_if_empty": 0,
   "fieldname": "custom_original_rate",
   "fieldtype": "Currency",
   "hidden": 0,
   "hide_border": 0,
   "hide_days": 0,
   "hide_seconds": 0,
   "idx": 30,
   "ignore_user_permissions": 0,
   "ignore_xss_filter": 0,
   "in_global_search": 0,
   "in_list_view": 0,
   "in_preview": 0,
   "in_standard_filter": 0,
   "insert_after": "custom_price_recon_col1",
   "is_system_generated": 0,
   "is_virtual": 0,
   "label": "Original Rate",
   "length": 0,
   "link_filters": null,
   "mandatory_depends_on": null,
   "modified": "2026-06-27 21:08:57.780177",
   "modified_by": "Administrator",
   "module": null,
   "name": "Sales Invoice Item-custom_original_rate",
   "no_copy": 0,
   "non_negative": 0,
   "options": "",
   "owner": "Administrator",
   "permlevel": 0,
   "placeholder": null,
   "precision": "",
   "print_hide": 0,
   "print_hide_if_no_value": 0,
   "print_width": null,
   "read_only": 0,
   "read_only_depends_on": null,
   "report_hide": 0,
   "reqd": 0,
   "search_index": 0,
   "show_dashboard": 0,
   "sort_options": 0,
   "translatable": 0,
   "unique": 0,
   "width": null
  },
  {
   "_assign": null,
   "_comments": null,
   "_liked_by": null,
   "_user_tags": null,
   "allow_in_quick_entry": 0,
   "allow_on_submit": 0,
   "bold": 0,
   "collapsible": 0,
   "collapsible_depends_on": null,
   "columns": 0,
   "creation": "2026-06-27 21:08:57.476270",
   "default": null,
   "depends_on": null,
   "description": null,
   "docstatus": 0,
   "dt": "Sales Invoice Item",
   "fetch_from": null,
   "fetch_if_empty": 0,
   "fieldname": "custom_price_recon_col1",
   "fieldtype": "Column Break",
   "hidden": 0,
   "hide_border": 0,
   "hide_days": 0,
   "hide_seconds": 0,
   "idx": 29,
   "ignore_user_permissions": 0,
   "ignore_xss_filter": 0,
   "in_global_search": 0,
   "in_list_view": 0,
   "in_preview": 0,
   "in_standard_filter": 0,
   "insert_after": "custom_pricing_reconciliation_section",
   "is_system_generated": 0,
   "is_virtual": 0,
   "label": "",
   "length": 0,
   "link_filters": null,
   "mandatory_depends_on": null,
   "modified": "2026-06-27 21:08:57.476270",
   "modified_by": "Administrator",
   "module": null,
   "name": "Sales Invoice Item-custom_price_recon_col1",
   "no_copy": 0,
   "non_negative": 0,
   "options": "",
   "owner": "Administrator",
   "permlevel": 0,
   "placeholder": null,
   "precision": "",
   "print_hide": 0,
   "print_hide_if_no_value": 0,
   "print_width": null,
   "read_only": 0,
   "read_only_depends_on": null,
   "report_hide": 0,
   "reqd": 0,
   "search_index": 0,
   "show_dashboard": 0,
   "sort_options": 0,
   "translatable": 0,
   "unique": 0,
   "width": null
  },
  {
   "_assign": null,
   "_comments": null,
   "_liked_by": null,
   "_user_tags": null,
   "allow_in_quick_entry": 0,
   "allow_on_submit": 0,
   "bold": 0,
   "collapsible": 0,
   "collapsible_depends_on": null,
   "columns": 0,
   "creation": "2026-06-27 21:08:58.830732",
   "default": null,
   "depends_on": null,
   "description": null,
   "docstatus": 0,
   "dt": "Sales Invoice Item",
   "fetch_from": null,
   "fetch_if_empty": 0,
   "fieldname": "custom_price_recon_col2",
   "fieldtype": "Column Break",
   "hidden": 0,
   "hide_border": 0,
   "hide_days": 0,
   "hide_seconds": 0,
   "idx": 33,
   "ignore_user_permissions": 0,
   "ignore_xss_filter": 0,
   "in_global_search": 0,
   "in_list_view": 0,
   "in_preview": 0,
   "in_standard_filter": 0,
   "insert_after": "custom_rate_override_reason",
   "is_system_generated": 0,
   "is_virtual": 0,
   "label": "",
   "length": 0,
   "link_filters": null,
   "mandatory_depends_on": null,
   "modified": "2026-06-27 21:08:58.830732",
   "modified_by": "Administrator",
   "module": null,
   "name": "Sales Invoice Item-custom_price_recon_col2",
   "no_copy": 0,
   "non_negative": 0,
   "options": "",
   "owner": "Administrator",
   "permlevel": 0,
   "placeholder": null,
   "precision": "",
   "print_hide": 0,
   "print_hide_if_no_value": 0,
   "print_width": null,
   "read_only": 0,
   "read_only_depends_on": null,
   "report_hide": 0,
   "reqd": 0,
   "search_index": 0,
   "show_dashboard": 0,
   "sort_options": 0,
   "translatable": 0,
   "unique": 0,
   "width": null
  },
  {
   "_assign": null,
   "_comments": null,
   "_liked_by": null,
   "_user_tags": null,
   "allow_in_quick_entry": 0,
   "allow_on_submit": 0,
   "bold": 0,
   "collapsible": 0,
   "collapsible_depends_on": null,
   "columns": 0,
   "creation": "2026-06-27 21:08:57.069142",
   "default": null,
   "depends_on": null,
   "description": null,
   "docstatus": 0,
   "dt": "Sales Invoice Item",
   "fetch_from": null,
   "fetch_if_empty": 0,
   "fieldname": "custom_pricing_reconciliation_section",
   "fieldtype": "Section Break",
   "hidden": 0,
   "hide_border": 0,
   "hide_days": 0,
   "hide_seconds": 0,
   "idx": 28,
   "ignore_user_permissions": 0,
   "ignore_xss_filter": 0,
   "in_global_search": 0,
   "in_list_view": 0,
   "in_preview": 0,
   "in_standard_filter": 0,
   "insert_after": "custom_billing_decision",
   "is_system_generated": 0,
   "is_virtual": 0,
   "label": "Pricing & Reconciliation",
   "length": 0,
   "link_filters": null,
   "mandatory_depends_on": null,
   "modified": "2026-06-27 21:08:57.069142",
   "modified_by": "Administrator",
   "module": null,
   "name": "Sales Invoice Item-custom_pricing_reconciliation_section",
   "no_copy": 0,
   "non_negative": 0,
   "options": "",
   "owner": "Administrator",
   "permlevel": 0,
   "placeholder": null,
   "precision": "",
   "print_hide": 0,
   "print_hide_if_no_value": 0,
   "print_width": null,
   "read_only": 0,
   "read_only_depends_on": null,
   "report_hide": 0,
   "reqd": 0,
   "search_index": 0,
   "show_dashboard": 0,
   "sort_options": 0,
   "translatable": 0,
   "unique": 0,
   "width": null
  },
  {
   "_assign": null,
   "_comments": null,
   "_liked_by": null,
   "_user_tags": null,
   "allow_in_quick_entry": 0,
   "allow_on_submit": 0,
   "bold": 0,
   "collapsible": 0,
   "collapsible_depends_on": null,
   "columns": 0,
   "creation": "2026-06-27 21:08:56.457997",
   "default": null,
   "depends_on": null,
   "description": null,
   "docstatus": 0,
   "dt": "Sales Invoice Item",
   "fetch_from": null,
   "fetch_if_empty": 0,
   "fieldname": "custom_rate_code",
   "fieldtype": "Select",
   "hidden": 0,
   "hide_border": 0,
   "hide_days": 0,
   "hide_seconds": 0,
   "idx": 26,
   "ignore_user_permissions": 0,
   "ignore_xss_filter": 0,
   "in_global_search": 0,
   "in_list_view": 0,
   "in_preview": 0,
   "in_standard_filter": 0,
   "insert_after": "custom_billing_attr_col2",
   "is_system_generated": 0,
   "is_virtual": 0,
   "label": "Rate Code",
   "length": 0,
   "link_filters": null,
   "mandatory_depends_on": null,
   "modified": "2026-06-27 21:08:56.457997",
   "modified_by": "Administrator",
   "module": null,
   "name": "Sales Invoice Item-custom_rate_code",
   "no_copy": 0,
   "non_negative": 0,
   "options": "USD0\nUSD1\nLOCAL0\nLOCAL1",
   "owner": "Administrator",
   "permlevel": 0,
   "placeholder": null,
   "precision": "",
   "print_hide": 0,
   "print_hide_if_no_value": 0,
   "print_width": null,
   "read_only": 0,
   "read_only_depends_on": null,
   "report_hide": 0,
   "reqd": 0,
   "search_index": 0,
   "show_dashboard": 0,
   "sort_options": 0,
   "translatable": 0,
   "unique": 0,
   "width": null
  },
  {
   "_assign": null,
   "_comments": null,
   "_liked_by": null,
   "_user_tags": null,
   "allow_in_quick_entry": 0,
   "allow_on_submit": 0,
   "bold": 0,
   "collapsible": 0,
   "collapsible_depends_on": null,
   "columns": 0,
   "creation": "2026-06-27 21:08:58.533211",
   "default": null,
   "depends_on": null,
   "description": null,
   "docstatus": 0,
   "dt": "Sales Invoice Item",
   "fetch_from": null,
   "fetch_if_empty": 0,
   "fieldname": "custom_rate_override_reason",
   "fieldtype": "Small Text",
   "hidden": 0,
   "hide_border": 0,
   "hide_days": 0,
   "hide_seconds": 0,
   "idx": 32,
   "ignore_user_permissions": 0,
   "ignore_xss_filter": 0,
   "in_global_search": 0,
   "in_list_view": 0,
   "in_preview": 0,
   "in_standard_filter": 0,
   "insert_after": "custom_final_rate",
   "is_system_generated": 0,
   "is_virtual": 0,
   "label": "Rate Override Reason",
   "length": 0,
   "link_filters": null,
   "mandatory_depends_on": null,
   "modified": "2026-06-27 21:08:58.533211",
   "modified_by": "Administrator",
   "module": null,
   "name": "Sales Invoice Item-custom_rate_override_reason",
   "no_copy": 0,
   "non_negative": 0,
   "options": "",
   "owner": "Administrator",
   "permlevel": 0,
   "placeholder": null,
   "precision": "",
   "print_hide": 0,
   "print_hide_if_no_value": 0,
   "print_width": null,
   "read_only": 0,
   "read_only_depends_on": null,
   "report_hide": 0,
   "reqd": 0,
   "search_index": 0,
   "show_dashboard": 0,
   "sort_options": 0,
   "translatable": 0,
   "unique": 0,
   "width": null
  },
  {
   "_assign": null,
   "_comments": null,
   "_liked_by": null,
   "_user_tags": null,
   "allow_in_quick_entry": 0,
   "allow_on_submit": 0,
   "bold": 0,
   "collapsible": 0,
   "collapsible_depends_on": null,
   "columns": 0,
   "creation": "2026-06-27 21:08:51.960358",
   "default": null,
   "depends_on": null,
   "description": null,
   "docstatus": 0,
   "dt": "Sales Invoice Item",
   "fetch_from": null,
   "fetch_if_empty": 0,
   "fieldname": "custom_registration_number",
   "fieldtype": "Data",
   "hidden": 0,
   "hide_border": 0,
   "hide_days": 0,
   "hide_seconds": 0,
   "idx": 14,
   "ignore_user_permissions": 0,
   "ignore_xss_filter": 0,
   "in_global_search": 0,
   "in_list_view": 0,
   "in_preview": 0,
   "in_standard_filter": 0,
   "insert_after": "custom_fleet_number",
   "is_system_generated": 0,
   "is_virtual": 0,
   "label": "Registration Number",
   "length": 0,
   "link_filters": null,
   "mandatory_depends_on": null,
   "modified": "2026-06-27 21:08:51.960358",
   "modified_by": "Administrator",
   "module": null,
   "name": "Sales Invoice Item-custom_registration_number",
   "no_copy": 0,
   "non_negative": 0,
   "options": "",
   "owner": "Administrator",
   "permlevel": 0,
   "placeholder": null,
   "precision": "",
   "print_hide": 0,
   "print_hide_if_no_value": 0,
   "print_width": null,
   "read_only": 0,
   "read_only_depends_on": null,
   "report_hide": 0,
   "reqd": 0,
   "search_index": 0,
   "show_dashboard": 0,
   "sort_options": 0,
   "translatable": 0,
   "unique": 0,
   "width": null
  },
  {
   "_assign": null,
   "_comments": null,
   "_liked_by": null,
   "_user_tags": null,
   "allow_in_quick_entry": 0,
   "allow_on_submit": 0,
   "bold": 0,
   "collapsible": 0,
   "collapsible_depends_on": null,
   "columns": 0,
   "creation": "2026-06-27 21:08:52.964151",
   "default": null,
   "depends_on": null,
   "description": null,
   "docstatus": 0,
   "dt": "Sales Invoice Item",
   "fetch_from": null,
   "fetch_if_empty": 0,
   "fieldname": "custom_source_job",
   "fieldtype": "Link",
   "hidden": 0,
   "hide_border": 0,
   "hide_days": 0,
   "hide_seconds": 0,
   "idx": 16,
   "ignore_user_permissions": 0,
   "ignore_xss_filter": 0,
   "in_global_search": 0,
   "in_list_view": 0,
   "in_preview": 0,
   "in_standard_filter": 0,
   "insert_after": "custom_fleet_details_col2",
   "is_system_generated": 0,
   "is_virtual": 0,
   "label": "Source Job",
   "length": 0,
   "link_filters": null,
   "mandatory_depends_on": null,
   "modified": "2026-06-27 21:08:52.964151",
   "modified_by": "Administrator",
   "module": null,
   "name": "Sales Invoice Item-custom_source_job",
   "no_copy": 0,
   "non_negative": 0,
   "options": "Job",
   "owner": "Administrator",
   "permlevel": 0,
   "placeholder": null,
   "precision": "",
   "print_hide": 0,
   "print_hide_if_no_value": 0,
   "print_width": null,
   "read_only": 0,
   "read_only_depends_on": null,
   "report_hide": 0,
   "reqd": 0,
   "search_index": 0,
   "show_dashboard": 0,
   "sort_options": 0,
   "translatable": 0,
   "unique": 0,
   "width": null
  },
  {
   "_assign": null,
   "_comments": null,
   "_liked_by": null,
   "_user_tags": null,
   "allow_in_quick_entry": 0,
   "allow_on_submit": 0,
   "bold": 0,
   "collapsible": 0,
   "collapsible_depends_on": null,
   "columns": 0,
   "creation": "2026-06-27 21:08:50.788487",
   "default": null,
   "depends_on": null,
   "description": null,
   "docstatus": 0,
   "dt": "Sales Invoice Item",
   "fetch_from": null,
   "fetch_if_empty": 0,
   "fieldname": "custom_vehicle",
   "fieldtype": "Link",
   "hidden": 0,
   "hide_border": 0,
   "hide_days": 0,
   "hide_seconds": 0,
   "idx": 11,
   "ignore_user_permissions": 0,
   "ignore_xss_filter": 0,
   "in_global_search": 0,
   "in_list_view": 0,
   "in_preview": 0,
   "in_standard_filter": 0,
   "insert_after": "custom_fleet_details_col1",
   "is_system_generated": 0,
   "is_virtual": 0,
   "label": "Vehicle",
   "length": 0,
   "link_filters": null,
   "mandatory_depends_on": null,
   "modified": "2026-06-27 21:08:50.788487",
   "modified_by": "Administrator",
   "module": null,
   "name": "Sales Invoice Item-custom_vehicle",
   "no_copy": 0,
   "non_negative": 0,
   "options": "Vehicle",
   "owner": "Administrator",
   "permlevel": 0,
   "placeholder": null,
   "precision": "",
   "print_hide": 0,
   "print_hide_if_no_value": 0,
   "print_width": null,
   "read_only": 0,
   "read_only_depends_on": null,
   "report_hide": 0,
   "reqd": 0,
   "search_index": 0,
   "show_dashboard": 0,
   "sort_options": 0,
   "translatable": 0,
   "unique": 0,
   "width": null
  },
  {
   "_assign": null,
   "_comments": null,
   "_liked_by": null,
   "_user_tags": null,
   "allow_in_quick_entry": 0,
   "allow_on_submit": 0,
   "bold": 0,
   "collapsible": 0,
   "collapsible_depends_on": null,
   "columns": 0,
   "creation": "2026-06-27 21:08:59.100037",
   "default": null,
   "depends_on": null,
   "description": null,
   "docstatus": 0,
   "dt": "Sales Invoice Item",
   "fetch_from": null,
   "fetch_if_empty": 0,
   "fieldname": "custom_waived",
   "fieldtype": "Check",
   "hidden": 0,
   "hide_border": 0,
   "hide_days": 0,
   "hide_seconds": 0,
   "idx": 34,
   "ignore_user_permissions": 0,
   "ignore_xss_filter": 0,
   "in_global_search": 0,
   "in_list_view": 0,
   "in_preview": 0,
   "in_standard_filter": 0,
   "insert_after": "custom_price_recon_col2",
   "is_system_generated": 0,
   "is_virtual": 0,
   "label": "Waived",
   "length": 0,
   "link_filters": null,
   "mandatory_depends_on": null,
   "modified": "2026-06-27 21:08:59.100037",
   "modified_by": "Administrator",
   "module": null,
   "name": "Sales Invoice Item-custom_waived",
   "no_copy": 0,
   "non_negative": 0,
   "options": "",
   "owner": "Administrator",
   "permlevel": 0,
   "placeholder": null,
   "precision": "",
   "print_hide": 0,
   "print_hide_if_no_value": 0,
   "print_width": null,
   "read_only": 0,
   "read_only_depends_on": null,
   "report_hide": 0,
   "reqd": 0,
   "search_index": 0,
   "show_dashboard": 0,
   "sort_options": 0,
   "translatable": 0,
   "unique": 0,
   "width": null
  },
  {
   "_assign": null,
   "_comments": null,
   "_liked_by": null,
   "_user_tags": null,
   "allow_in_quick_entry": 0,
   "allow_on_submit": 0,
   "bold": 0,
   "collapsible": 0,
   "collapsible_depends_on": null,
   "columns": 0,
   "creation": "2026-06-27 21:08:59.416240",
   "default": null,
   "depends_on": null,
   "description": null,
   "docstatus": 0,
   "dt": "Sales Invoice Item",
   "fetch_from": null,
   "fetch_if_empty": 0,
   "fieldname": "custom_waiver_reason",
   "fieldtype": "Small Text",
   "hidden": 0,
   "hide_border": 0,
   "hide_days": 0,
   "hide_seconds": 0,
   "idx": 35,
   "ignore_user_permissions": 0,
   "ignore_xss_filter": 0,
   "in_global_search": 0,
   "in_list_view": 0,
   "in_preview": 0,
   "in_standard_filter": 0,
   "insert_after": "custom_waived",
   "is_system_generated": 0,
   "is_virtual": 0,
   "label": "Waiver Reason",
   "length": 0,
   "link_filters": null,
   "mandatory_depends_on": null,
   "modified": "2026-06-27 21:08:59.416240",
   "modified_by": "Administrator",
   "module": null,
   "name": "Sales Invoice Item-custom_waiver_reason",
   "no_copy": 0,
   "non_negative": 0,
   "options": "",
   "owner": "Administrator",
   "permlevel": 0,
   "placeholder": null,
   "precision": "",
   "print_hide": 0,
   "print_hide_if_no_value": 0,
   "print_width": null,
   "read_only": 0,
   "read_only_depends_on": null,
   "report_hide": 0,
   "reqd": 0,
   "search_index": 0,
   "show_dashboard": 0,
   "sort_options": 0,
   "translatable": 0,
   "unique": 0,
   "width": null
  },
  {
   "_assign": null,
   "_comments": null,
   "_liked_by": null,
   "_user_tags": null,
   "allow_in_quick_entry": 0,
   "allow_on_submit": 0,
   "bold": 0,
   "collapsible": 0,
   "collapsible_depends_on": null,
   "columns": 0,
   "creation": "2026-07-09 13:00:00.000000",
   "default": null,
   "depends_on": null,
   "description": null,
   "docstatus": 0,
   "dt": "Sales Invoice Item",
   "fetch_from": null,
   "fetch_if_empty": 0,
   "fieldname": "custom_last_activity_date",
   "fieldtype": "Date",
   "hidden": 0,
   "hide_border": 0,
   "hide_days": 0,
   "hide_seconds": 0,
   "idx": 35,
   "ignore_user_permissions": 0,
   "ignore_xss_filter": 0,
   "in_global_search": 0,
   "in_list_view": 0,
   "in_preview": 0,
   "in_standard_filter": 0,
   "insert_after": "custom_waiver_reason",
   "is_system_generated": 0,
   "is_virtual": 0,
   "label": "Last Activity Date",
   "length": 0,
   "link_filters": null,
   "mandatory_depends_on": null,
   "modified": "2026-07-09 13:00:00.000000",
   "modified_by": "Administrator",
   "module": null,
   "name": "Sales Invoice Item-custom_last_activity_date",
   "no_copy": 0,
   "non_negative": 0,
   "options": "",
   "owner": "Administrator",
   "permlevel": 0,
   "placeholder": null,
   "precision": "",
   "print_hide": 0,
   "print_hide_if_no_value": 0,
   "print_width": null,
   "read_only": 0,
   "read_only_depends_on": null,
   "report_hide": 0,
   "reqd": 0,
   "search_index": 0,
   "show_dashboard": 0,
   "sort_options": 0,
   "translatable": 0,
   "unique": 0,
   "width": null
  },
  {
   "_assign": null,
   "_comments": null,
   "_liked_by": null,
   "_user_tags": null,
   "allow_in_quick_entry": 0,
   "allow_on_submit": 0,
   "bold": 0,
   "collapsible": 0,
   "collapsible_depends_on": null,
   "columns": 0,
   "creation": "2026-07-09 13:00:00.000000",
   "default": null,
   "depends_on": null,
   "description": null,
   "docstatus": 0,
   "dt": "Sales Invoice Item",
   "fetch_from": null,
   "fetch_if_empty": 0,
   "fieldname": "custom_active_status_cutoff_day",
   "fieldtype": "Int",
   "hidden": 0,
   "hide_border": 0,
   "hide_days": 0,
   "hide_seconds": 0,
   "idx": 36,
   "ignore_user_permissions": 0,
   "ignore_xss_filter": 0,
   "in_global_search": 0,
   "in_list_view": 0,
   "in_preview": 0,
   "in_standard_filter": 0,
   "insert_after": "custom_last_activity_date",
   "is_system_generated": 0,
   "is_virtual": 0,
   "label": "Active Status Cutoff Day",
   "length": 0,
   "link_filters": null,
   "mandatory_depends_on": null,
   "modified": "2026-07-09 13:00:00.000000",
   "modified_by": "Administrator",
   "module": null,
   "name": "Sales Invoice Item-custom_active_status_cutoff_day",
   "no_copy": 0,
   "non_negative": 0,
   "options": "",
   "owner": "Administrator",
   "permlevel": 0,
   "placeholder": null,
   "precision": "",
   "print_hide": 0,
   "print_hide_if_no_value": 0,
   "print_width": null,
   "read_only": 0,
   "read_only_depends_on": null,
   "report_hide": 0,
   "reqd": 0,
   "search_index": 0,
   "show_dashboard": 0,
   "sort_options": 0,
   "translatable": 0,
   "unique": 0,
   "width": null
  }
 ],
 "custom_perms": [],
 "doctype": "Sales Invoice Item",
 "links": [],
 "property_setters": [
  {
   "_assign": null,
   "_comments": null,
   "_liked_by": null,
   "_user_tags": null,
   "creation": "2026-06-19 16:50:51.547696",
   "default_value": null,
   "doc_type": "Sales Invoice Item",
   "docstatus": 0,
   "doctype_or_field": "DocField",
   "field_name": "barcode",
   "idx": 0,
   "is_system_generated": 1,
   "modified": "2026-07-02 20:59:58.466159",
   "modified_by": "Administrator",
   "module": null,
   "name": "Sales Invoice Item-barcode-hidden",
   "owner": "Administrator",
   "property": "hidden",
   "property_type": "Check",
   "row_name": null,
   "value": "0"
  },
  {
   "_assign": null,
   "_comments": null,
   "_liked_by": null,
   "_user_tags": null,
   "creation": "2026-06-06 20:29:03.406814",
   "default_value": null,
   "doc_type": "Sales Invoice Item",
   "docstatus": 0,
   "doctype_or_field": "DocField",
   "field_name": "discount_account",
   "idx": 0,
   "is_system_generated": 1,
   "modified": "2026-07-02 20:59:58.532294",
   "modified_by": "Administrator",
   "module": null,
   "name": "Sales Invoice Item-discount_account-hidden",
   "owner": "Administrator",
   "property": "hidden",
   "property_type": "Check",
   "row_name": null,
   "value": "1"
  },
  {
   "_assign": null,
   "_comments": null,
   "_liked_by": null,
   "_user_tags": null,
   "creation": "2026-06-06 20:29:03.450153",
   "default_value": null,
   "doc_type": "Sales Invoice Item",
   "docstatus": 0,
   "doctype_or_field": "DocField",
   "field_name": "discount_account",
   "idx": 0,
   "is_system_generated": 1,
   "modified": "2026-07-02 20:59:58.589295",
   "modified_by": "Administrator",
   "module": null,
   "name": "Sales Invoice Item-discount_account-mandatory_depends_on",
   "owner": "Administrator",
   "property": "mandatory_depends_on",
   "property_type": "Code",
   "row_name": null,
   "value": ""
  },
  {
   "_assign": null,
   "_comments": null,
   "_liked_by": null,
   "_user_tags": null,
   "creation": "2026-07-02 21:13:37.131756",
   "default_value": null,
   "doc_type": "Sales Invoice Item",
   "docstatus": 0,
   "doctype_or_field": "DocType",
   "field_name": null,
   "idx": 0,
   "is_system_generated": 0,
   "modified": "2026-07-02 21:13:37.131756",
   "modified_by": "Administrator",
   "module": null,
   "name": "Sales Invoice Item-main-field_order",
   "owner": "Administrator",
   "property": "field_order",
   "property_type": "Data",
   "row_name": null,
   "value": "[\"barcode\", \"has_item_scanned\", \"item_code\", \"col_break1\", \"item_name\", \"customer_item_code\", \"description_section\", \"description\", \"custom_fleet_details_section\", \"custom_fleet_details_col1\", \"custom_vehicle\", \"custom_device_number\", \"custom_fleet_number\", \"custom_registration_number\", \"custom_fleet_details_col2\", \"custom_source_job\", \"custom_billing_month_label\", \"custom_custom_biling_month\", \"custom_billing_attributes_section\", \"custom_billing_attr_col1\", \"custom_is_subscription\", \"custom_is_installation\", \"custom_is_component\", \"custom_included\", \"custom_billing_attr_col2\", \"custom_rate_code\", \"custom_billing_decision\", \"custom_pricing_reconciliation_section\", \"custom_price_recon_col1\", \"custom_original_rate\", \"custom_final_rate\", \"custom_rate_override_reason\", \"custom_price_recon_col2\", \"custom_waived\", \"custom_waiver_reason\", \"item_group\", \"brand\", \"image_section\", \"image\", \"image_view\", \"quantity_and_rate\", \"qty\", \"stock_uom\", \"col_break2\", \"uom\", \"conversion_factor\", \"stock_qty\", \"section_break_17\", \"price_list_rate\", \"base_price_list_rate\", \"discount_and_margin\", \"margin_type\", \"margin_rate_or_amount\", \"rate_with_margin\", \"column_break_19\", \"discount_percentage\", \"discount_amount\", \"distributed_discount_amount\", \"base_rate_with_margin\", \"section_break1\", \"rate\", \"amount\", \"item_tax_template\", \"col_break3\", \"base_rate\", \"base_amount\", \"pricing_rules\", \"stock_uom_rate\", \"is_free_item\", \"grant_commission\", \"section_break_21\", \"net_rate\", \"net_amount\", \"column_break_24\", \"base_net_rate\", \"base_net_amount\", \"drop_ship\", \"delivered_by_supplier\", \"accounting\", \"income_account\", \"is_fixed_asset\", \"asset\", \"finance_book\", \"col_break4\", \"expense_account\", \"discount_account\", \"deferred_revenue\", \"deferred_revenue_account\", \"service_stop_date\", \"enable_deferred_revenue\", \"column_break_50\", \"service_start_date\", \"service_end_date\", \"section_break_18\", \"weight_per_unit\", \"total_weight\", \"column_break_21\", \"weight_uom\", \"warehouse_and_reference\", \"warehouse\", \"target_warehouse\", \"quality_inspection\", \"pick_serial_and_batch\", \"serial_and_batch_bundle\", \"use_serial_batch_fields\", \"col_break5\", \"allow_zero_valuation_rate\", \"incoming_rate\", \"item_tax_rate\", \"actual_batch_qty\", \"section_break_eoec\", \"serial_no\", \"column_break_ytgd\", \"batch_no\", \"available_quantity_section\", \"actual_qty\", \"column_break_ogff\", \"company_total_stock\", \"edit_references\", \"sales_order\", \"so_detail\", \"sales_invoice_item\", \"column_break_74\", \"delivery_note\", \"dn_detail\", \"delivered_qty\", \"column_break_vwhb\", \"pos_invoice\", \"pos_invoice_item\", \"internal_transfer_section\", \"purchase_order\", \"column_break_92\", \"purchase_order_item\", \"accounting_dimensions_section\", \"cost_center\", \"dimension_col_break\", \"project\", \"section_break_54\", \"page_break\"]"
  }
 ],
 "sync_on_migrate": 1
}